backend.v
`include "serial_data.v"

module testbench();

    reg i_resetbAll;
    reg i_clk;
    reg i_sclk;
    reg i_sdin;
    reg i_vco_clk;

    wire o_ready;
    wire o_resetb1;
    wire [1:0] o_gainA1;
    wire o_resetb2;
    wire [2:0] o_gainA2;
    wire o_resetbvco;
    


    initial begin
        $monitor("%t %b %b %b %b %b %b ",$time,o_ready, o_resetb1, o_resetb2, o_gainA1, o_gainA2, o_resetbvco);
        // $monitor("%t iclk: %b; i_sclk: %b; i_sdin: %b; %b %b",$time,i_clk,i_sclk,i_sdin,o_gainA1,o_gainA2);
    end

    initial begin
        $dumpfile("backend.vcd");
        $dumpvars(0,testbench);
    end
        
    backend bk(i_resetbAll,
                i_clk,
                i_sclk,
                i_sdin,
                i_vco_clk,
                o_ready,
                o_resetb1,
                o_gainA1,
                o_resetb2,
                o_gainA2,
                o_resetbvco);

    initial begin
        i_clk = 0;
        i_resetbAll = 1;
        i_sclk = 0;
        i_sdin = 0;
        i_vco_clk = 0; 
        #5 i_resetbAll = 0;
        #15 i_resetbAll = 1;
        // $display("%t",$time);
        #20 i_sdin = 1;
        #30 i_sdin = 0;
        #30 i_sdin = 0;
        #30 i_sdin = 1;
        #30 i_sdin = 1;
        #30 i_sdin = 0;
        #700 $finish;   
    end 
    always #15 i_sclk = ~i_sclk;
    always #10 i_clk = ~i_clk; 
    
    



endmodule



module backend (
    i_resetbAll,
    i_clk,
    i_sclk,
    i_sdin,
    i_vco_clk,
    o_ready,
    o_resetb1,
    o_gainA1,
    o_resetb2,
    o_gainA2,
    o_resetbvco
);
    input i_resetbAll;
    input i_clk;
    input i_sclk;
    input i_sdin;
    input i_vco_clk;

    output reg o_ready;
    output reg o_resetb1;
    output reg [1:0] o_gainA1;
    output reg o_resetb2;
    output reg [2:0] o_gainA2;
    output reg o_resetbvco;
    
//    wire [4:0] data;
    // initial begin
    //     data = 5'd0;
    // end
    integer  i;

    always @(negedge(i_resetbAll)) begin
        o_ready = 0;
        o_resetb1 = 0;
        o_gainA1 = 2'd0;
        o_resetb2 = 0;
        o_gainA2 = 3'd0;
        o_resetbvco = 0;
        // data = 5'd0;
    end
    // serialData sd(i_sclk,i_sdin,o_gainA1);
    always @(posedge(i_resetbAll)) begin
        
        @(posedge(i_sclk));
        @(posedge(i_sclk));
        o_gainA1[0] = i_sdin;

        @(posedge(i_sclk));
        o_gainA1[1] = i_sdin;
        // repeat(2)begin
        //     @(posedge(i_sclk));
        //     o_gainA1[i] = i_sdin;
        // end

        for(i=0;i<3;i=i+1)begin
            @(posedge(i_sclk));
            o_gainA2[i] = i_sdin;
        end
        // // o_gainA1 = data[1-:2];
        // // o_gainA2 = data[4-:3];
        // $display("%t",$time);
        // for(i=0;i<2;i++)begin
        //     @(posedge(i_clk));
        //     @(posedge(i_clk));
        // end
        
        // $display("%t",$time);
        // $display("%t",$time);
        repeat(2)begin
            @(posedge(i_clk));
        end
        o_resetbvco = 1;

        repeat(10)begin
            @(posedge(i_clk));
        end
        o_resetb1 = 1;
        o_resetb2 = 1;
        repeat(10)begin
            @(posedge(i_clk));
        end
        o_ready = 1;
    end


endmodule

backend.vcd
$date
	Sat Oct 22 18:09:06 2022
$end
$version
	Icarus Verilog
$end
$timescale
	1s
$end
$scope module testbench $end
$var wire 1 ! o_resetbvco $end
$var wire 1 " o_resetb2 $end
$var wire 1 # o_resetb1 $end
$var wire 1 $ o_ready $end
$var wire 3 % o_gainA2 [2:0] $end
$var wire 2 & o_gainA1 [1:0] $end
$var reg 1 ' i_clk $end
$var reg 1 ( i_resetbAll $end
$var reg 1 ) i_sclk $end
$var reg 1 * i_sdin $end
$var reg 1 + i_vco_clk $end
$scope module bk $end
$var wire 1 ' i_clk $end
$var wire 1 ( i_resetbAll $end
$var wire 1 ) i_sclk $end
$var wire 1 * i_sdin $end
$var wire 1 + i_vco_clk $end
$var reg 2 , o_gainA1 [1:0] $end
$var reg 3 - o_gainA2 [2:0] $end
$var reg 1 $ o_ready $end
$var reg 1 # o_resetb1 $end
$var reg 1 " o_resetb2 $end
$var reg 1 ! o_resetbvco $end
$var integer 32 . i [31:0] $end
$upscope $end
$upscope $end
$enddefinitions $end
$comment Show the parameter values. $end
$dumpall
$end
#0
$dumpvars
bx .
bx -
bx ,
0+
0*
0)
1(
0'
bx &
bx %
x$
x#
x"
x!
$end
#5
0!
b0 %
b0 -
0"
b0 &
b0 ,
0#
0$
0(
#10
1'
#15
1)
#20
0'
1(
#30
1'
0)
#40
0'
1*
#45
b1 &
b1 ,
1)
#50
1'
#60
0'
0)
#70
1'
0*
#75
b0 .
1)
#80
0'
#90
1'
0)
#100
0'
#105
b1 .
1)
#110
1'
#120
0'
0)
#130
1'
1*
#135
b10 .
b10 %
b10 -
1)
#140
0'
#150
1'
0)
#160
0'
#165
b11 .
b110 %
b110 -
1)
#170
1'
#180
0'
0)
#190
1!
1'
0*
#195
1)
#200
0'
#210
1'
0)
#220
0'
#225
1)
#230
1'
#240
0'
0)
#250
1'
#255
1)
#260
0'
#270
1'
0)
#280
0'
#285
1)
#290
1'
#300
0'
0)
#310
1'
#315
1)
#320
0'
#330
1'
0)
#340
0'
#345
1)
#350
1'
#360
0'
0)
#370
1'
#375
1)
#380
0'
#390
1"
1#
1'
0)
#400
0'
#405
1)
#410
1'
#420
0'
0)
#430
1'
#435
1)
#440
0'
#450
1'
0)
#460
0'
#465
1)
#470
1'
#480
0'
0)
#490
1'
#495
1)
#500
0'
#510
1'
0)
#520
0'
#525
1)
#530
1'
#540
0'
0)
#550
1'
#555
1)
#560
0'
#570
1'
0)
#580
0'
#585
1)
#590
1$
1'
