backend.v
module backend (
    i_resetbAll,
    i_clk,
    i_sclk,
    i_sdin,
    i_vco_clk,
    o_ready,
    o_resetb1,
    o_gainA1,
    o_resetb2,
    o_gainA2,
    o_resetbvco
);
    input i_resetbAll;
    input i_clk;
    input i_sclk;
    input i_sdin;
    input i_vco_clk;

    output reg o_ready;
    output reg o_resetb1;
    output reg [1:0] o_gainA1;
    output reg o_resetb2;
    output reg [2:0] o_gainA2;
    output reg o_resetbvco;
    
    integer  i;
    reg k;
    initial k = 0; // State for frequency estimation
    

    // ################################################################################

    // Reset Registers

    always @(negedge(i_resetbAll)) begin
        o_ready = 0;
        o_resetb1 = 0;
        o_gainA1 = 2'd0;
        o_resetb2 = 0;
        o_gainA2 = 3'd0;
        o_resetbvco = 0;
        k = 0;
    end


    // ################################################################################

    // Serial Data communication 
    
    always @(posedge(i_resetbAll)) begin
        
        for(i=0;i<2;i=i+1)begin // Runs for two positive edges of i_sclk and reads the serial data into o_gainA1
            @(posedge(i_sclk));
            o_gainA1[i] = i_sdin;
        end


        for(i=0;i<3;i=i+1)begin // Runs for three positive edges of i_sclk and reads the serial data into o_gainA2
            @(posedge(i_sclk));
            o_gainA2[i] = i_sdin;
        end

        repeat(2)begin         // Waits for two clock cycles and then sets o_resetbvco
            @(posedge(i_clk));
        end
        o_resetbvco = 1;

        repeat(10)begin         // Waits for ten clock cycles and then sets o_resetb1 and o_resetb2
            @(posedge(i_clk));
        end
        o_resetb1 = 1;
        o_resetb2 = 1;

        repeat(10)begin         // Waits for ten clock cycles and then sets o_ready
            @(posedge(i_clk));
        end
        o_ready = 1;
    end

    // ################################################################################

    // Frequency Estimator

    real mainf = 0;
    real vcof = 0;
    real vco_freq = 0;

    always @(posedge(i_resetbAll)) begin
        k = 1;
    end

    always @(posedge(i_clk) && k) begin
        mainf = mainf + 1;
        if(mainf==10000)begin
            @(posedge(i_vco_clk));
            vco_freq = (vcof*200)/mainf;
            $display("\n i_vco_frequency: %0.3f MHz\n",vco_freq);
            k = 0;
            mainf = 0;
            vcof = 0;
            $finish; // Finishes after estimating the frequency;
        end
    end

    always @(posedge(i_vco_clk) && k) begin
        vcof = vcof + 1;
    end


    // ################################################################################

endmodule

FPGA_model.v
///////////////////////////////////////////////////////////////////////////////
/*FPGA model
 * Generates reset signal for the chip
 * Sends out progamming bits to the chip
*/
module FPGA_model(	i_resetbFPGA,
			i_ready,
			i_mainclk,
			o_resetbAll,
			o_sclk, 
			o_sdout);

//============================================================================
//Parameter declarations
parameter opcode_gainA1	= 2; //range: 0-3. Gain for amplifier 1
parameter opcode_gainA2	= 5; //range: 0-7. Gain for amplifier 2

//FPGA states
parameter sRESET 	= 0; //Reset all internal variables. Make o_resetbAll=0.
parameter sPROGRAM	= 1; //Send programming bits to chip.
parameter sIDLE		= 2; //Do nothing.
//===========================================================================
//Input output declarations
input i_resetbFPGA; 		//resets FPGA
input i_ready;			//Alerts FPGA that chip is programmed and ready
input i_mainclk;		//Main clock
output reg o_resetbAll;		//Reset for the chip
output reg o_sclk;		//Serial clock for communication
output reg o_sdout;		//Serial data out from FPGA (to chip)


//Internal wire, reg declarations
reg [1:0] FPGAstate;		//Holds the state of FPGA
reg [3:0] count;		//Used for controlling sclk generation and transmission of serial data
reg mainclkby2, mainclkby4, mainclkby8, mainclkby16; //Low frequency clocks derived from mainclk

//=============================================================
//BEHAVIORAL DESCRIPTION
//=============================================================
// Setting the FPGA state
always @ (posedge(i_mainclk) or negedge(i_resetbFPGA))
begin
	if(i_resetbFPGA == 0)
		FPGAstate <= sRESET;
	else
	begin
		case(FPGAstate)
		sRESET: FPGAstate <= sPROGRAM;
		sPROGRAM: 
		begin	
			if(count== 10)
				FPGAstate <= sIDLE;
			else
				FPGAstate <= sPROGRAM;
		end
		sIDLE: FPGAstate <=sIDLE;
		default: FPGAstate <= sIDLE;
		endcase
	end
end
//========================================================
/*resetbALL
 * resetbAll=0, when FPGA is reset. 
 * resetbAll=1 at all other times.
*/
always @(posedge(i_mainclk) or negedge(i_resetbFPGA))
begin
	if(i_resetbFPGA == 0)
		o_resetbAll <= 0;
	else
	begin
		if(FPGAstate == sRESET)
			o_resetbAll <= 0;
		else
			o_resetbAll <= 1;
	end
end
//==========================================================
/* Generation of low frequency clocks from mainclk using divide-by-2 method
*/
always @ (posedge(i_mainclk) or negedge(i_resetbFPGA))
begin
	if(i_resetbFPGA == 0)
		mainclkby2 <= 0;
	else
		mainclkby2 <= ~mainclkby2;
end

always @ (posedge(mainclkby2) or negedge(i_resetbFPGA))
begin
	if(i_resetbFPGA == 0)
		mainclkby4 <= 0;
	else
		mainclkby4 <= ~mainclkby4;
end

always @(posedge(mainclkby4) or negedge(i_resetbFPGA))
begin
	if(i_resetbFPGA == 0)
		mainclkby8 <= 0;
	else
		mainclkby8 <= ~mainclkby8;
end

always @(posedge(mainclkby8) or negedge(i_resetbFPGA))
begin
	if(i_resetbFPGA == 0)
		mainclkby16 <= 0;
	else
		mainclkby16 <= ~mainclkby16;
end
//==========================================================
/*count
 * used for the generation of sclk and selecting the data to be sent in through sdin
 */
always	@(posedge(mainclkby16) or negedge(i_resetbFPGA))
begin
	if(i_resetbFPGA == 0)
		count <= 0;
	else
	begin
		if(FPGAstate == sPROGRAM)
		begin
			if(count == 11)
				count <= count;
			else
				count <= count+1;
		end
		else
			count <= count;
	end
end
//=========================================================
/*sclk
 * sclk is a clock only when the FPGA is programming the chip.
 */
always @ (posedge(mainclkby16) or negedge(i_resetbFPGA))
begin
	if(i_resetbFPGA == 0)
		o_sclk <= 1;
	else
	begin
		if(FPGAstate == sPROGRAM)
		begin
			if (count >= 1 && count <= 10)
				o_sclk <= ~o_sclk;
			else
				o_sclk <= 1;
		end
		else
			o_sclk <= 1;
	end
end

//=========================================================
/*sdin
 *serial data out from FPGA
 */
always @ (negedge(o_sclk) or negedge(i_resetbFPGA))
begin
	if(i_resetbFPGA == 0)
		o_sdout <= 0;
	else
	begin
		if(FPGAstate == sPROGRAM)
		begin
			case(count)
			4'd2: o_sdout <= opcode_gainA1[0];
			4'd4: o_sdout <= opcode_gainA1[1];
			4'd6: o_sdout <= opcode_gainA2[0];
			4'd8: o_sdout <= opcode_gainA2[1];
			4'd10: o_sdout <= opcode_gainA2[2];
			default: o_sdout <= o_sdout;
			endcase
		end
		else
			o_sdout <= 0;
		
	end
end
//==========================================================
endmodule

backend_tb.v
// Testbanch module for the backend. This is has a module instantiation for
// the FPGA_model and the backend.
`timescale 1ns / 1ps
//==========================================================================
//Change the Verilog filenames approppriately.
`include "FPGA_model.v"
`include "backend.v"
//=========================================================================

module backend_tb();

reg resetbFPGA;
reg main_clk;

wire [1:0]gainA1 ; 
wire [2:0]gainA2 ;
wire resetbAll, resetb1, resetb2, resetbvco; 
reg vco_clk;
wire sclk, sdin;
wire ready;

initial begin
	$monitor("%t %b %b %b %b %b %b",$time,ready, resetb1, resetb2, gainA1, gainA2, resetbvco);
end

//==========================================================================
//FPGA model instantiation
FPGA_model   FPGA_obj(	.i_resetbFPGA (resetbFPGA),
			.i_ready (ready),
			.o_resetbAll (resetbAll),
			.i_mainclk (main_clk),
			.o_sclk (sclk), 
			.o_sdout (sdin));

// Backend instantiation 
backend backend_obj (	.i_resetbAll (resetbAll),
			.i_clk (main_clk),
			.i_sclk (sclk),
			.i_sdin (sdin),
			.i_vco_clk (vco_clk),
			.o_ready (ready),
			.o_resetb1 (resetb1),
			.o_gainA1 (gainA1),
			.o_resetb2 (resetb2),
			.o_gainA2 (gainA2),
			.o_resetbvco (resetbvco)
			);
//============================================================================
    initial begin
        $dumpfile("backend_tb.vcd");
        $dumpvars(0,backend_tb);
    end

//Test signal generation
initial
begin
	resetbFPGA <= 0;
	main_clk <= 0;
	vco_clk <= 0;
	#1 resetbFPGA <= 1;
	// #10000 $finish;
end

//Generation of main_clk 
always #2.5 main_clk <= ~main_clk;
always #3.65 vco_clk <= ~vco_clk; // Vco_clk frequency can change to a different frequency to estimate it.
//============================================================================
endmodule

backend_tb.vcd
$date
	Tue Oct 25 20:56:47 2022
$end
$version
	Icarus Verilog
$end
$timescale
	1ps
$end
$scope module backend_tb $end
$var wire 1 ! sdin $end
$var wire 1 " sclk $end
$var wire 1 # resetbvco $end
$var wire 1 $ resetbAll $end
$var wire 1 % resetb2 $end
$var wire 1 & resetb1 $end
$var wire 1 ' ready $end
$var wire 3 ( gainA2 [2:0] $end
$var wire 2 ) gainA1 [1:0] $end
$var reg 1 * main_clk $end
$var reg 1 + resetbFPGA $end
$var reg 1 , vco_clk $end
$scope module FPGA_obj $end
$var wire 1 * i_mainclk $end
$var wire 1 + i_resetbFPGA $end
$var wire 1 ' i_ready $end
$var parameter 32 - opcode_gainA1 $end
$var parameter 32 . opcode_gainA2 $end
$var parameter 32 / sIDLE $end
$var parameter 32 0 sPROGRAM $end
$var parameter 32 1 sRESET $end
$var reg 2 2 FPGAstate [1:0] $end
$var reg 4 3 count [3:0] $end
$var reg 1 4 mainclkby16 $end
$var reg 1 5 mainclkby2 $end
$var reg 1 6 mainclkby4 $end
$var reg 1 7 mainclkby8 $end
$var reg 1 $ o_resetbAll $end
$var reg 1 " o_sclk $end
$var reg 1 ! o_sdout $end
$upscope $end
$scope module backend_obj $end
$var wire 1 * i_clk $end
$var wire 1 $ i_resetbAll $end
$var wire 1 " i_sclk $end
$var wire 1 ! i_sdin $end
$var wire 1 , i_vco_clk $end
$var reg 1 8 k $end
$var reg 2 9 o_gainA1 [1:0] $end
$var reg 3 : o_gainA2 [2:0] $end
$var reg 1 ' o_ready $end
$var reg 1 & o_resetb1 $end
$var reg 1 % o_resetb2 $end
$var reg 1 # o_resetbvco $end
$var integer 32 ; i [31:0] $end
$var real 1 < mainf $end
$var real 1 = vco_freq $end
$var real 1 > vcof $end
$upscope $end
$upscope $end
$enddefinitions $end
$comment Show the parameter values. $end
$dumpall
b0 1
b1 0
b10 /
b101 .
b10 -
$end
#0
$dumpvars
r0 >
r0 =
r0 <
bx ;
b0 :
b0 9
08
07
06
05
04
b0 3
b0 2
0,
0+
0*
b0 )
b0 (
0'
0&
0%
0$
0#
1"
0!
$end
#1000
1+
#2500
b1 3
14
17
16
15
b1 2
1*
#3650
1,
#5000
0*
#7300
0,
#7500
r1 <
b0 ;
18
1$
05
1*
#10000
0*
#10950
r1 >
1,
#12500
06
15
r2 <
1*
#14600
0,
#15000
0*
#17500
05
r3 <
1*
#18250
r2 >
1,
#20000
0*
#21900
0,
#22500
07
16
15
r4 <
1*
#25000
0*
#25550
r3 >
1,
#27500
05
r5 <
1*
#29200
0,
#30000
0*
#32500
06
15
r6 <
1*
#32850
r4 >
1,
#35000
0*
#36500
0,
#37500
05
r7 <
1*
#40000
0*
#40150
r5 >
1,
#42500
04
17
16
15
r8 <
1*
#43800
0,
#45000
0*
#47450
r6 >
1,
#47500
05
r9 <
1*
#50000
0*
#51100
0,
#52500
06
15
r10 <
1*
#54750
r7 >
1,
#55000
0*
#57500
05
r11 <
1*
#58400
0,
#60000
0*
#62050
r8 >
1,
#62500
07
16
15
r12 <
1*
#65000
0*
#65700
0,
#67500
05
r13 <
1*
#69350
r9 >
1,
#70000
0*
#72500
06
15
r14 <
1*
#73000
0,
#75000
0*
#76650
r10 >
1,
#77500
05
r15 <
1*
#80000
0*
#80300
0,
#82500
b10 3
0"
14
17
16
15
r16 <
1*
#83950
r11 >
1,
#85000
0*
#87500
05
r17 <
1*
#87600
0,
#90000
0*
#91250
r12 >
1,
#92500
06
15
r18 <
1*
#94900
0,
#95000
0*
#97500
05
r19 <
1*
#98550
r13 >
1,
#100000
0*
#102200
0,
#102500
07
16
15
r20 <
1*
#105000
0*
#105850
r14 >
1,
#107500
05
r21 <
1*
#109500
0,
#110000
0*
#112500
06
15
r22 <
1*
#113150
r15 >
1,
#115000
0*
#116800
0,
#117500
05
r23 <
1*
#120000
0*
#120450
r16 >
1,
#122500
04
17
16
15
r24 <
1*
#124100
0,
#125000
0*
#127500
05
r25 <
1*
#127750
r17 >
1,
#130000
0*
#131400
0,
#132500
06
15
r26 <
1*
#135000
0*
#135050
r18 >
1,
#137500
05
r27 <
1*
#138700
0,
#140000
0*
#142350
r19 >
1,
#142500
07
16
15
r28 <
1*
#145000
0*
#146000
0,
#147500
05
r29 <
1*
#149650
r20 >
1,
#150000
0*
#152500
06
15
r30 <
1*
#153300
0,
#155000
0*
#156950
r21 >
1,
#157500
05
r31 <
1*
#160000
0*
#160600
0,
#162500
b1 ;
1"
b11 3
14
17
16
15
r32 <
1*
#164250
r22 >
1,
#165000
0*
#167500
05
r33 <
1*
#167900
0,
#170000
0*
#171550
r23 >
1,
#172500
06
15
r34 <
1*
#175000
0*
#175200
0,
#177500
05
r35 <
1*
#178850
r24 >
1,
#180000
0*
#182500
07
16
15
r36 <
1*
0,
#185000
0*
#186150
r25 >
1,
#187500
05
r37 <
1*
#189800
0,
#190000
0*
#192500
06
15
r38 <
1*
#193450
r26 >
1,
#195000
0*
#197100
0,
#197500
05
r39 <
1*
#200000
0*
#200750
r27 >
1,
#202500
04
17
16
15
r40 <
1*
#204400
0,
#205000
0*
#207500
05
r41 <
1*
#208050
r28 >
1,
#210000
0*
#211700
0,
#212500
06
15
r42 <
1*
#215000
0*
#215350
r29 >
1,
#217500
05
r43 <
1*
#219000
0,
#220000
0*
#222500
07
16
15
r44 <
1*
#222650
r30 >
1,
#225000
0*
#226300
0,
#227500
05
r45 <
1*
#229950
r31 >
1,
#230000
0*
#232500
06
15
r46 <
1*
#233600
0,
#235000
0*
#237250
r32 >
1,
#237500
05
r47 <
1*
#240000
0*
#240900
0,
#242500
1!
b100 3
0"
14
17
16
15
r48 <
1*
#244550
r33 >
1,
#245000
0*
#247500
05
r49 <
1*
#248200
0,
#250000
0*
#251850
r34 >
1,
#252500
06
15
r50 <
1*
#255000
0*
#255500
0,
#257500
05
r51 <
1*
#259150
r35 >
1,
#260000
0*
#262500
07
16
15
r52 <
1*
#262800
0,
#265000
0*
#266450
r36 >
1,
#267500
05
r53 <
1*
#270000
0*
#270100
0,
#272500
06
15
r54 <
1*
#273750
r37 >
1,
#275000
0*
#277400
0,
#277500
05
r55 <
1*
#280000
0*
#281050
r38 >
1,
#282500
04
17
16
15
r56 <
1*
#284700
0,
#285000
0*
#287500
05
r57 <
1*
#288350
r39 >
1,
#290000
0*
#292000
0,
#292500
06
15
r58 <
1*
#295000
0*
#295650
r40 >
1,
#297500
05
r59 <
1*
#299300
0,
#300000
0*
#302500
07
16
15
r60 <
1*
#302950
r41 >
1,
#305000
0*
#306600
0,
#307500
05
r61 <
1*
#310000
0*
#310250
r42 >
1,
#312500
06
15
r62 <
1*
#313900
0,
#315000
0*
#317500
05
r63 <
1*
#317550
r43 >
1,
#320000
0*
#321200
0,
#322500
b0 ;
b10 )
b10 9
1"
b101 3
14
17
16
15
r64 <
1*
#324850
r44 >
1,
#325000
0*
#327500
05
r65 <
1*
#328500
0,
#330000
0*
#332150
r45 >
1,
#332500
06
15
r66 <
1*
#335000
0*
#335800
0,
#337500
05
r67 <
1*
#339450
r46 >
1,
#340000
0*
#342500
07
16
15
r68 <
1*
#343100
0,
#345000
0*
#346750
r47 >
1,
#347500
05
r69 <
1*
#350000
0*
#350400
0,
#352500
06
15
r70 <
1*
#354050
r48 >
1,
#355000
0*
#357500
05
r71 <
1*
#357700
0,
#360000
0*
#361350
r49 >
1,
#362500
04
17
16
15
r72 <
1*
#365000
0*
0,
#367500
05
r73 <
1*
#368650
r50 >
1,
#370000
0*
#372300
0,
#372500
06
15
r74 <
1*
#375000
0*
#375950
r51 >
1,
#377500
05
r75 <
1*
#379600
0,
#380000
0*
#382500
07
16
15
r76 <
1*
#383250
r52 >
1,
#385000
0*
#386900
0,
#387500
05
r77 <
1*
#390000
0*
#390550
r53 >
1,
#392500
06
15
r78 <
1*
#394200
0,
#395000
0*
#397500
05
r79 <
1*
#397850
r54 >
1,
#400000
0*
#401500
0,
#402500
b110 3
0"
14
17
16
15
r80 <
1*
#405000
0*
#405150
r55 >
1,
#407500
05
r81 <
1*
#408800
0,
#410000
0*
#412450
r56 >
1,
#412500
06
15
r82 <
1*
#415000
0*
#416100
0,
#417500
05
r83 <
1*
#419750
r57 >
1,
#420000
0*
#422500
07
16
15
r84 <
1*
#423400
0,
#425000
0*
#427050
r58 >
1,
#427500
05
r85 <
1*
#430000
0*
#430700
0,
#432500
06
15
r86 <
1*
#434350
r59 >
1,
#435000
0*
#437500
05
r87 <
1*
#438000
0,
#440000
0*
#441650
r60 >
1,
#442500
04
17
16
15
r88 <
1*
#445000
0*
#445300
0,
#447500
05
r89 <
1*
#448950
r61 >
1,
#450000
0*
#452500
06
15
r90 <
1*
#452600
0,
#455000
0*
#456250
r62 >
1,
#457500
05
r91 <
1*
#459900
0,
#460000
0*
#462500
07
16
15
r92 <
1*
#463550
r63 >
1,
#465000
0*
#467200
0,
#467500
05
r93 <
1*
#470000
0*
#470850
r64 >
1,
#472500
06
15
r94 <
1*
#474500
0,
#475000
0*
#477500
05
r95 <
1*
#478150
r65 >
1,
#480000
0*
#481800
0,
#482500
b1 ;
b1 (
b1 :
1"
b111 3
14
17
16
15
r96 <
1*
#485000
0*
#485450
r66 >
1,
#487500
05
r97 <
1*
#489100
0,
#490000
0*
#492500
06
15
r98 <
1*
#492750
r67 >
1,
#495000
0*
#496400
0,
#497500
05
r99 <
1*
#500000
0*
#500050
r68 >
1,
#502500
07
16
15
r100 <
1*
#503700
0,
#505000
0*
#507350
r69 >
1,
#507500
05
r101 <
1*
#510000
0*
#511000
0,
#512500
06
15
r102 <
1*
#514650
r70 >
1,
#515000
0*
#517500
05
r103 <
1*
#518300
0,
#520000
0*
#521950
r71 >
1,
#522500
04
17
16
15
r104 <
1*
#525000
0*
#525600
0,
#527500
05
r105 <
1*
#529250
r72 >
1,
#530000
0*
#532500
06
15
r106 <
1*
#532900
0,
#535000
0*
#536550
r73 >
1,
#537500
05
r107 <
1*
#540000
0*
#540200
0,
#542500
07
16
15
r108 <
1*
#543850
r74 >
1,
#545000
0*
#547500
05
r109 <
1*
0,
#550000
0*
#551150
r75 >
1,
#552500
06
15
r110 <
1*
#554800
0,
#555000
0*
#557500
05
r111 <
1*
#558450
r76 >
1,
#560000
0*
#562100
0,
#562500
0!
b1000 3
0"
14
17
16
15
r112 <
1*
#565000
0*
#565750
r77 >
1,
#567500
05
r113 <
1*
#569400
0,
#570000
0*
#572500
06
15
r114 <
1*
#573050
r78 >
1,
#575000
0*
#576700
0,
#577500
05
r115 <
1*
#580000
0*
#580350
r79 >
1,
#582500
07
16
15
r116 <
1*
#584000
0,
#585000
0*
#587500
05
r117 <
1*
#587650
r80 >
1,
#590000
0*
#591300
0,
#592500
06
15
r118 <
1*
#594950
r81 >
1,
#595000
0*
#597500
05
r119 <
1*
#598600
0,
#600000
0*
#602250
r82 >
1,
#602500
04
17
16
15
r120 <
1*
#605000
0*
#605900
0,
#607500
05
r121 <
1*
#609550
r83 >
1,
#610000
0*
#612500
06
15
r122 <
1*
#613200
0,
#615000
0*
#616850
r84 >
1,
#617500
05
r123 <
1*
#620000
0*
#620500
0,
#622500
07
16
15
r124 <
1*
#624150
r85 >
1,
#625000
0*
#627500
05
r125 <
1*
#627800
0,
#630000
0*
#631450
r86 >
1,
#632500
06
15
r126 <
1*
#635000
0*
#635100
0,
#637500
05
r127 <
1*
#638750
r87 >
1,
#640000
0*
#642400
0,
#642500
b10 ;
1"
b1001 3
14
17
16
15
r128 <
1*
#645000
0*
#646050
r88 >
1,
#647500
05
r129 <
1*
#649700
0,
#650000
0*
#652500
06
15
r130 <
1*
#653350
r89 >
1,
#655000
0*
#657000
0,
#657500
05
r131 <
1*
#660000
0*
#660650
r90 >
1,
#662500
07
16
15
r132 <
1*
#664300
0,
#665000
0*
#667500
05
r133 <
1*
#667950
r91 >
1,
#670000
0*
#671600
0,
#672500
06
15
r134 <
1*
#675000
0*
#675250
r92 >
1,
#677500
05
r135 <
1*
#678900
0,
#680000
0*
#682500
04
17
16
15
r136 <
1*
#682550
r93 >
1,
#685000
0*
#686200
0,
#687500
05
r137 <
1*
#689850
r94 >
1,
#690000
0*
#692500
06
15
r138 <
1*
#693500
0,
#695000
0*
#697150
r95 >
1,
#697500
05
r139 <
1*
#700000
0*
#700800
0,
#702500
07
16
15
r140 <
1*
#704450
r96 >
1,
#705000
0*
#707500
05
r141 <
1*
#708100
0,
#710000
0*
#711750
r97 >
1,
#712500
06
15
r142 <
1*
#715000
0*
#715400
0,
#717500
05
r143 <
1*
#719050
r98 >
1,
#720000
0*
#722500
1!
b1010 3
0"
14
17
16
15
r144 <
1*
#722700
0,
#725000
0*
#726350
r99 >
1,
#727500
b10 2
05
r145 <
1*
#730000
0*
0,
#732500
06
15
r146 <
1*
#733650
r100 >
1,
#735000
0*
#737300
0,
#737500
05
r147 <
1*
#740000
0*
#740950
r101 >
1,
#742500
07
16
15
r148 <
1*
#744600
0,
#745000
0*
#747500
05
r149 <
1*
#748250
r102 >
1,
#750000
0*
#751900
0,
#752500
06
15
r150 <
1*
#755000
0*
#755550
r103 >
1,
#757500
05
r151 <
1*
#759200
0,
#760000
0*
#762500
04
17
16
15
r152 <
1*
#762850
r104 >
1,
#765000
0*
#766500
0,
#767500
05
r153 <
1*
#770000
0*
#770150
r105 >
1,
#772500
06
15
r154 <
1*
#773800
0,
#775000
0*
#777450
r106 >
1,
#777500
05
r155 <
1*
#780000
0*
#781100
0,
#782500
07
16
15
r156 <
1*
#784750
r107 >
1,
#785000
0*
#787500
05
r157 <
1*
#788400
0,
#790000
0*
#792050
r108 >
1,
#792500
06
15
r158 <
1*
#795000
0*
#795700
0,
#797500
05
r159 <
1*
#799350
r109 >
1,
#800000
0*
#802500
b11 ;
b101 (
b101 :
1"
14
17
16
15
r160 <
1*
#803000
0,
#805000
0*
#806650
r110 >
1,
#807500
05
r161 <
1*
#810000
0*
#810300
0,
#812500
06
15
r162 <
1#
1*
#813950
r111 >
1,
#815000
0*
#817500
05
r163 <
1*
#817600
0,
#820000
0*
#821250
r112 >
1,
#822500
07
16
15
r164 <
1*
#824900
0,
#825000
0*
#827500
05
r165 <
1*
#828550
r113 >
1,
#830000
0*
#832200
0,
#832500
06
15
r166 <
1*
#835000
0*
#835850
r114 >
1,
#837500
05
r167 <
1*
#839500
0,
#840000
0*
#842500
04
17
16
15
r168 <
1*
#843150
r115 >
1,
#845000
0*
#846800
0,
#847500
05
r169 <
1*
#850000
0*
#850450
r116 >
1,
#852500
06
15
r170 <
1*
#854100
0,
#855000
0*
#857500
05
r171 <
1*
#857750
r117 >
1,
#860000
0*
#861400
0,
#862500
07
16
15
r172 <
1%
1&
1*
#865000
0*
#865050
r118 >
1,
#867500
05
r173 <
1*
#868700
0,
#870000
0*
#872350
r119 >
1,
#872500
06
15
r174 <
1*
#875000
0*
#876000
0,
#877500
05
r175 <
1*
#879650
r120 >
1,
#880000
0*
#882500
14
17
16
15
r176 <
1*
#883300
0,
#885000
0*
#886950
r121 >
1,
#887500
05
r177 <
1*
#890000
0*
#890600
0,
#892500
06
15
r178 <
1*
#894250
r122 >
1,
#895000
0*
#897500
05
r179 <
1*
#897900
0,
#900000
0*
#901550
r123 >
1,
#902500
07
16
15
r180 <
1*
#905000
0*
#905200
0,
#907500
05
r181 <
1*
#908850
r124 >
1,
#910000
0*
#912500
06
15
r182 <
1'
1*
0,
#915000
0*
#916150
r125 >
1,
#917500
05
r183 <
1*
#919800
0,
#920000
0*
#922500
04
17
16
15
r184 <
1*
#923450
r126 >
1,
#925000
0*
#927100
0,
#927500
05
r185 <
1*
#930000
0*
#930750
r127 >
1,
#932500
06
15
r186 <
1*
#934400
0,
#935000
0*
#937500
05
r187 <
1*
#938050
r128 >
1,
#940000
0*
#941700
0,
#942500
07
16
15
r188 <
1*
#945000
0*
#945350
r129 >
1,
#947500
05
r189 <
1*
#949000
0,
#950000
0*
#952500
06
15
r190 <
1*
#952650
r130 >
1,
#955000
0*
#956300
0,
#957500
05
r191 <
1*
#959950
r131 >
1,
#960000
0*
#962500
14
17
16
15
r192 <
1*
#963600
0,
#965000
0*
#967250
r132 >
1,
#967500
05
r193 <
1*
#970000
0*
#970900
0,
#972500
06
15
r194 <
1*
#974550
r133 >
1,
#975000
0*
#977500
05
r195 <
1*
#978200
0,
#980000
0*
#981850
r134 >
1,
#982500
07
16
15
r196 <
1*
#985000
0*
#985500
0,
#987500
05
r197 <
1*
#989150
r135 >
1,
#990000
0*
#992500
06
15
r198 <
1*
#992800
0,
#995000
0*
#996450
r136 >
1,
#997500
05
r199 <
1*
#1000000
0*
#1000100
0,
#1002500
04
17
16
15
r200 <
1*
#1003750
r137 >
1,
#1005000
0*
#1007400
0,
#1007500
05
r201 <
1*
#1010000
0*
#1011050
r138 >
1,
#1012500
06
15
r202 <
1*
#1014700
0,
#1015000
0*
#1017500
05
r203 <
1*
#1018350
r139 >
1,
#1020000
0*
#1022000
0,
#1022500
07
16
15
r204 <
1*
#1025000
0*
#1025650
r140 >
1,
#1027500
05
r205 <
1*
#1029300
0,
#1030000
0*
#1032500
06
15
r206 <
1*
#1032950
r141 >
1,
#1035000
0*
#1036600
0,
#1037500
05
r207 <
1*
#1040000
0*
#1040250
r142 >
1,
#1042500
14
17
16
15
r208 <
1*
#1043900
0,
#1045000
0*
#1047500
05
r209 <
1*
#1047550
r143 >
1,
#1050000
0*
#1051200
0,
#1052500
06
15
r210 <
1*
#1054850
r144 >
1,
#1055000
0*
#1057500
05
r211 <
1*
#1058500
0,
#1060000
0*
#1062150
r145 >
1,
#1062500
07
16
15
r212 <
1*
#1065000
0*
#1065800
0,
#1067500
05
r213 <
1*
#1069450
r146 >
1,
#1070000
0*
#1072500
06
15
r214 <
1*
#1073100
0,
#1075000
0*
#1076750
r147 >
1,
#1077500
05
r215 <
1*
#1080000
0*
#1080400
0,
#1082500
04
17
16
15
r216 <
1*
#1084050
r148 >
1,
#1085000
0*
#1087500
05
r217 <
1*
#1087700
0,
#1090000
0*
#1091350
r149 >
1,
#1092500
06
15
r218 <
1*
#1095000
0*
0,
#1097500
05
r219 <
1*
#1098650
r150 >
1,
#1100000
0*
#1102300
0,
#1102500
07
16
15
r220 <
1*
#1105000
0*
#1105950
r151 >
1,
#1107500
05
r221 <
1*
#1109600
0,
#1110000
0*
#1112500
06
15
r222 <
1*
#1113250
r152 >
1,
#1115000
0*
#1116900
0,
#1117500
05
r223 <
1*
#1120000
0*
#1120550
r153 >
1,
#1122500
14
17
16
15
r224 <
1*
#1124200
0,
#1125000
0*
#1127500
05
r225 <
1*
#1127850
r154 >
1,
#1130000
0*
#1131500
0,
#1132500
06
15
r226 <
1*
#1135000
0*
#1135150
r155 >
1,
#1137500
05
r227 <
1*
#1138800
0,
#1140000
0*
#1142450
r156 >
1,
#1142500
07
16
15
r228 <
1*
#1145000
0*
#1146100
0,
#1147500
05
r229 <
1*
#1149750
r157 >
1,
#1150000
0*
#1152500
06
15
r230 <
1*
#1153400
0,
#1155000
0*
#1157050
r158 >
1,
#1157500
05
r231 <
1*
#1160000
0*
#1160700
0,
#1162500
04
17
16
15
r232 <
1*
#1164350
r159 >
1,
#1165000
0*
#1167500
05
r233 <
1*
#1168000
0,
#1170000
0*
#1171650
r160 >
1,
#1172500
06
15
r234 <
1*
#1175000
0*
#1175300
0,
#1177500
05
r235 <
1*
#1178950
r161 >
1,
#1180000
0*
#1182500
07
16
15
r236 <
1*
#1182600
0,
#1185000
0*
#1186250
r162 >
1,
#1187500
05
r237 <
1*
#1189900
0,
#1190000
0*
#1192500
06
15
r238 <
1*
#1193550
r163 >
1,
#1195000
0*
#1197200
0,
#1197500
05
r239 <
1*
#1200000
0*
#1200850
r164 >
1,
#1202500
14
17
16
15
r240 <
1*
#1204500
0,
#1205000
0*
#1207500
05
r241 <
1*
#1208150
r165 >
1,
#1210000
0*
#1211800
0,
#1212500
06
15
r242 <
1*
#1215000
0*
#1215450
r166 >
1,
#1217500
05
r243 <
1*
#1219100
0,
#1220000
0*
#1222500
07
16
15
r244 <
1*
#1222750
r167 >
1,
#1225000
0*
#1226400
0,
#1227500
05
r245 <
1*
#1230000
0*
#1230050
r168 >
1,
#1232500
06
15
r246 <
1*
#1233700
0,
#1235000
0*
#1237350
r169 >
1,
#1237500
05
r247 <
1*
#1240000
0*
#1241000
0,
#1242500
04
17
16
15
r248 <
1*
#1244650
r170 >
1,
#1245000
0*
#1247500
05
r249 <
1*
#1248300
0,
#1250000
0*
#1251950
r171 >
1,
#1252500
06
15
r250 <
1*
#1255000
0*
#1255600
0,
#1257500
05
r251 <
1*
#1259250
r172 >
1,
#1260000
0*
#1262500
07
16
15
r252 <
1*
#1262900
0,
#1265000
0*
#1266550
r173 >
1,
#1267500
05
r253 <
1*
#1270000
0*
#1270200
0,
#1272500
06
15
r254 <
1*
#1273850
r174 >
1,
#1275000
0*
#1277500
05
r255 <
1*
0,
#1280000
0*
#1281150
r175 >
1,
#1282500
14
17
16
15
r256 <
1*
#1284800
0,
#1285000
0*
#1287500
05
r257 <
1*
#1288450
r176 >
1,
#1290000
0*
#1292100
0,
#1292500
06
15
r258 <
1*
#1295000
0*
#1295750
r177 >
1,
#1297500
05
r259 <
1*
#1299400
0,
#1300000
0*
#1302500
07
16
15
r260 <
1*
#1303050
r178 >
1,
#1305000
0*
#1306700
0,
#1307500
05
r261 <
1*
#1310000
0*
#1310350
r179 >
1,
#1312500
06
15
r262 <
1*
#1314000
0,
#1315000
0*
#1317500
05
r263 <
1*
#1317650
r180 >
1,
#1320000
0*
#1321300
0,
#1322500
04
17
16
15
r264 <
1*
#1324950
r181 >
1,
#1325000
0*
#1327500
05
r265 <
1*
#1328600
0,
