frequency_estimator.v
`timescale 1ns / 1ps

module frequency_tb ();
    reg main_clk;
    reg vco_clk;
    wire [10:0] freq;
    reg i_resetbAll;
    initial begin
        i_resetbAll = 0;
        main_clk = 0;
        vco_clk = 0;
        #5 i_resetbAll = 1;
        // #2500 $finish;
        // #10000
    end
    initial begin
        $dumpfile("frequency_tb.vcd");
        $dumpvars(0,frequency_tb);
    end
    // initial $monitor("%d",freq);
    frequency_estimator f(main_clk,vco_clk,i_resetbAll,freq);


    always #2.5 main_clk = ~main_clk;
    always #3.425 vco_clk = ~vco_clk;

endmodule


module frequency_estimator (
    main_clk,
    vco_clk,
    i_resetbAll,
    freq
);
    input main_clk,vco_clk,i_resetbAll;
    output reg [10:0] freq;

    integer mainf = 0;
    integer vcof = 0;
    integer ans = 0;
    always @(posedge(main_clk) && i_resetbAll) begin
        mainf = mainf + 1;
        if(mainf==10000)begin
            @(posedge(vco_clk))
            vcof = vcof +1;
            $display("%d %d",mainf,vcof);
            ans = (vcof*200)/mainf;
            freq = ans;
            $display("%d",ans);
            #1000 $finish;
        end
    end

    always @(posedge(vco_clk) && i_resetbAll) begin
        vcof = vcof + 1;
    end

endmodule

frequency_tb.vcd
$date
	Tue Oct 25 16:08:27 2022
$end
$version
	Icarus Verilog
$end
$timescale
	1ps
$end
$scope module frequency_tb $end
$var wire 11 ! freq [10:0] $end
$var reg 1 " i_resetbAll $end
$var reg 1 # main_clk $end
$var reg 1 $ vco_clk $end
$scope module f $end
$var wire 1 " i_resetbAll $end
$var wire 1 # main_clk $end
$var wire 1 $ vco_clk $end
$var reg 11 % freq [10:0] $end
$var integer 32 & ans [31:0] $end
$var integer 32 ' mainf [31:0] $end
$var integer 32 ( vcof [31:0] $end
$upscope $end
$upscope $end
$enddefinitions $end
$comment Show the parameter values. $end
$dumpall
$end
#0
$dumpvars
b0 (
b0 '
b0 &
bx %
0$
0#
0"
bx !
$end
#2500
1#
#3425
1$
#5000
b1 (
0#
1"
#6850
0$
#7500
b1 '
1#
#10000
0#
#10275
b10 (
1$
#12500
b10 '
1#
#13700
0$
#15000
0#
#17125
b11 (
1$
#17500
b11 '
1#
#20000
0#
#20550
0$
#22500
b100 '
1#
#23975
b100 (
1$
#25000
0#
#27400
0$
#27500
b101 '
1#
#30000
0#
#30825
b101 (
1$
#32500
b110 '
1#
#34250
0$
#35000
0#
#37500
b111 '
1#
#37675
b110 (
1$
#40000
0#
#41100
0$
#42500
b1000 '
1#
#44525
b111 (
1$
#45000
0#
#47500
b1001 '
1#
#47950
0$
#50000
0#
#51375
b1000 (
1$
#52500
b1010 '
1#
#54800
0$
#55000
0#
#57500
b1011 '
1#
#58225
b1001 (
1$
#60000
0#
#61650
0$
#62500
b1100 '
1#
#65000
0#
#65075
b1010 (
1$
#67500
b1101 '
1#
#68500
0$
#70000
0#
#71925
b1011 (
1$
#72500
b1110 '
1#
#75000
0#
#75350
0$
#77500
b1111 '
1#
#78775
b1100 (
1$
#80000
0#
#82200
0$
#82500
b10000 '
1#
#85000
0#
#85625
b1101 (
1$
#87500
b10001 '
1#
#89050
0$
#90000
0#
#92475
b1110 (
1$
#92500
b10010 '
1#
#95000
0#
#95900
0$
#97500
b10011 '
1#
#99325
b1111 (
1$
#100000
0#
#102500
b10100 '
1#
#102750
0$
#105000
0#
#106175
b10000 (
1$
#107500
b10101 '
1#
#109600
0$
#110000
0#
#112500
b10110 '
1#
#113025
b10001 (
1$
#115000
0#
#116450
0$
#117500
b10111 '
1#
#119875
b10010 (
1$
#120000
0#
#122500
b11000 '
1#
#123300
0$
#125000
0#
#126725
b10011 (
1$
#127500
b11001 '
1#
#130000
0#
#130150
0$
#132500
b11010 '
1#
#133575
b10100 (
1$
#135000
0#
#137000
0$
#137500
b11011 '
1#
#140000
0#
#140425
b10101 (
1$
#142500
b11100 '
1#
#143850
0$
#145000
0#
#147275
b10110 (
1$
#147500
b11101 '
1#
#150000
0#
#150700
0$
#152500
b11110 '
1#
#154125
b10111 (
1$
#155000
0#
#157500
b11111 '
1#
#157550
0$
#160000
0#
#160975
b11000 (
1$
#162500
b100000 '
1#
#164400
0$
#165000
0#
#167500
b100001 '
1#
#167825
b11001 (
1$
#170000
0#
#171250
0$
#172500
b100010 '
1#
#174675
b11010 (
1$
#175000
0#
#177500
b100011 '
1#
#178100
0$
#180000
0#
#181525
b11011 (
1$
#182500
b100100 '
1#
#184950
0$
#185000
0#
#187500
b100101 '
1#
#188375
b11100 (
1$
#190000
0#
#191800
0$
#192500
b100110 '
1#
#195000
0#
#195225
b11101 (
1$
#197500
b100111 '
1#
#198650
0$
#200000
0#
#202075
b11110 (
1$
#202500
b101000 '
1#
#205000
0#
#205500
0$
#207500
b101001 '
1#
#208925
b11111 (
1$
#210000
0#
#212350
0$
#212500
b101010 '
1#
#215000
0#
#215775
b100000 (
1$
#217500
b101011 '
1#
#219200
0$
#220000
0#
#222500
b101100 '
1#
#222625
b100001 (
1$
#225000
0#
#226050
0$
#227500
b101101 '
1#
#229475
b100010 (
1$
#230000
0#
#232500
b101110 '
1#
#232900
0$
#235000
0#
#236325
b100011 (
1$
#237500
b101111 '
1#
#239750
0$
#240000
0#
#242500
b110000 '
1#
#243175
b100100 (
1$
#245000
0#
#246600
0$
#247500
b110001 '
1#
#250000
0#
#250025
b100101 (
1$
#252500
b110010 '
1#
#253450
0$
#255000
0#
#256875
b100110 (
1$
#257500
b110011 '
1#
#260000
0#
#260300
0$
#262500
b110100 '
1#
#263725
b100111 (
1$
#265000
0#
#267150
0$
#267500
b110101 '
1#
#270000
0#
#270575
b101000 (
1$
#272500
b110110 '
1#
#274000
0$
#275000
0#
#277425
b101001 (
1$
#277500
b110111 '
1#
#280000
0#
#280850
0$
#282500
b111000 '
1#
#284275
b101010 (
1$
#285000
0#
#287500
b111001 '
1#
#287700
0$
#290000
0#
#291125
b101011 (
1$
#292500
b111010 '
1#
#294550
0$
#295000
0#
#297500
b111011 '
1#
#297975
b101100 (
1$
#300000
0#
#301400
0$
#302500
b111100 '
1#
#304825
b101101 (
1$
#305000
0#
#307500
b111101 '
1#
#308250
0$
#310000
0#
#311675
b101110 (
1$
#312500
b111110 '
1#
#315000
0#
#315100
0$
#317500
b111111 '
1#
#318525
b101111 (
1$
#320000
0#
#321950
0$
#322500
b1000000 '
1#
#325000
0#
#325375
b110000 (
1$
#327500
b1000001 '
1#
#328800
0$
#330000
0#
#332225
b110001 (
1$
#332500
b1000010 '
1#
#335000
0#
#335650
0$
#337500
b1000011 '
1#
#339075
b110010 (
1$
#340000
0#
#342500
b1000100 '
1#
0$
#345000
0#
#345925
b110011 (
1$
#347500
b1000101 '
1#
#349350
0$
#350000
0#
#352500
b1000110 '
1#
#352775
b110100 (
1$
#355000
0#
#356200
0$
#357500
b1000111 '
1#
#359625
b110101 (
1$
#360000
0#
#362500
b1001000 '
1#
#363050
0$
#365000
0#
#366475
b110110 (
1$
#367500
b1001001 '
1#
#369900
0$
#370000
0#
#372500
b1001010 '
1#
#373325
b110111 (
1$
#375000
0#
#376750
0$
#377500
b1001011 '
1#
#380000
0#
#380175
b111000 (
1$
#382500
b1001100 '
1#
#383600
0$
#385000
0#
#387025
b111001 (
1$
#387500
b1001101 '
1#
#390000
0#
#390450
0$
#392500
b1001110 '
1#
#393875
b111010 (
1$
#395000
0#
#397300
0$
#397500
b1001111 '
1#
#400000
0#
#400725
b111011 (
1$
#402500
b1010000 '
1#
#404150
0$
#405000
0#
#407500
b1010001 '
1#
#407575
b111100 (
1$
#410000
0#
#411000
0$
#412500
b1010010 '
1#
#414425
b111101 (
1$
#415000
0#
#417500
b1010011 '
1#
#417850
0$
#420000
0#
#421275
b111110 (
1$
#422500
b1010100 '
1#
#424700
0$
#425000
0#
#427500
b1010101 '
1#
#428125
b111111 (
1$
#430000
0#
#431550
0$
#432500
b1010110 '
1#
#434975
b1000000 (
1$
#435000
0#
#437500
b1010111 '
1#
#438400
0$
#440000
0#
#441825
b1000001 (
1$
#442500
b1011000 '
1#
#445000
0#
#445250
0$
#447500
b1011001 '
1#
#448675
b1000010 (
1$
#450000
0#
#452100
0$
#452500
b1011010 '
1#
#455000
0#
#455525
b1000011 (
1$
#457500
b1011011 '
1#
#458950
0$
#460000
0#
#462375
b1000100 (
1$
#462500
b1011100 '
1#
#465000
0#
#465800
0$
#467500
b1011101 '
1#
#469225
b1000101 (
1$
#470000
0#
#472500
b1011110 '
1#
#472650
0$
#475000
0#
#476075
b1000110 (
1$
#477500
b1011111 '
1#
#479500
0$
#480000
0#
#482500
b1100000 '
1#
#482925
b1000111 (
1$
#485000
0#
#486350
0$
#487500
b1100001 '
1#
#489775
b1001000 (
1$
#490000
0#
#492500
b1100010 '
1#
#493200
0$
#495000
0#
#496625
b1001001 (
1$
#497500
b1100011 '
1#
#500000
0#
#500050
0$
#502500
b1100100 '
1#
#503475
b1001010 (
1$
#505000
0#
#506900
0$
#507500
b1100101 '
1#
#510000
0#
#510325
b1001011 (
1$
#512500
b1100110 '
1#
#513750
0$
#515000
0#
#517175
b1001100 (
1$
#517500
b1100111 '
1#
#520000
0#
#520600
0$
#522500
b1101000 '
1#
#524025
b1001101 (
1$
#525000
0#
#527450
0$
#527500
b1101001 '
1#
#530000
0#
#530875
b1001110 (
1$
#532500
b1101010 '
1#
#534300
0$
#535000
0#
#537500
b1101011 '
1#
#537725
b1001111 (
1$
#540000
0#
#541150
0$
#542500
b1101100 '
1#
#544575
b1010000 (
1$
#545000
0#
#547500
b1101101 '
1#
#548000
0$
#550000
0#
#551425
b1010001 (
1$
#552500
b1101110 '
1#
#554850
0$
#555000
0#
#557500
b1101111 '
1#
#558275
b1010010 (
1$
#560000
0#
#561700
0$
#562500
b1110000 '
1#
#565000
0#
#565125
b1010011 (
1$
#567500
b1110001 '
1#
#568550
0$
#570000
0#
#571975
b1010100 (
1$
#572500
b1110010 '
1#
#575000
0#
#575400
0$
#577500
b1110011 '
1#
#578825
b1010101 (
1$
#580000
0#
#582250
0$
#582500
b1110100 '
1#
#585000
0#
#585675
b1010110 (
1$
#587500
b1110101 '
1#
#589100
0$
#590000
0#
#592500
b1110110 '
1#
#592525
b1010111 (
1$
#595000
0#
#595950
0$
#597500
b1110111 '
1#
#599375
b1011000 (
1$
#600000
0#
#602500
b1111000 '
1#
#602800
0$
#605000
0#
#606225
b1011001 (
1$
#607500
b1111001 '
1#
#609650
0$
#610000
0#
#612500
b1111010 '
1#
#613075
b1011010 (
1$
#615000
0#
#616500
0$
#617500
b1111011 '
1#
#619925
b1011011 (
1$
#620000
0#
#622500
b1111100 '
1#
#623350
0$
#625000
0#
#626775
b1011100 (
1$
#627500
b1111101 '
1#
#630000
0#
#630200
0$
#632500
b1111110 '
1#
#633625
b1011101 (
1$
#635000
0#
#637050
0$
#637500
b1111111 '
1#
#640000
0#
#640475
b1011110 (
1$
#642500
b10000000 '
1#
#643900
0$
#645000
0#
#647325
b1011111 (
1$
#647500
b10000001 '
1#
#650000
0#
#650750
0$
#652500
b10000010 '
1#
#654175
b1100000 (
1$
#655000
0#
#657500
b10000011 '
1#
#657600
0$
#660000
0#
#661025
b1100001 (
1$
#662500
b10000100 '
1#
#664450
0$
#665000
0#
#667500
b10000101 '
1#
#667875
b1100010 (
1$
#670000
0#
#671300
0$
#672500
b10000110 '
1#
#674725
b1100011 (
1$
#675000
0#
#677500
b10000111 '
1#
#678150
0$
#680000
0#
#681575
b1100100 (
1$
#682500
b10001000 '
1#
#685000
0#
0$
#687500
b10001001 '
1#
#688425
b1100101 (
1$
#690000
0#
#691850
0$
#692500
b10001010 '
1#
#695000
0#
#695275
b1100110 (
1$
#697500
b10001011 '
1#
#698700
0$
#700000
0#
#702125
b1100111 (
1$
#702500
b10001100 '
1#
#705000
0#
#705550
0$
#707500
b10001101 '
1#
#708975
b1101000 (
1$
#710000
0#
#712400
0$
#712500
b10001110 '
1#
#715000
0#
#715825
b1101001 (
1$
#717500
b10001111 '
1#
#719250
0$
#720000
0#
#722500
b10010000 '
1#
#722675
b1101010 (
1$
#725000
0#
#726100
0$
#727500
b10010001 '
1#
#729525
b1101011 (
1$
#730000
0#
#732500
b10010010 '
1#
#732950
0$
#735000
0#
#736375
b1101100 (
1$
#737500
b10010011 '
1#
#739800
0$
#740000
0#
#742500
b10010100 '
1#
#743225
b1101101 (
1$
#745000
0#
#746650
0$
#747500
b10010101 '
1#
#750000
0#
#750075
b1101110 (
1$
#752500
b10010110 '
1#
#753500
0$
#755000
0#
#756925
b1101111 (
1$
#757500
b10010111 '
1#
#760000
0#
#760350
0$
#762500
b10011000 '
1#
#763775
b1110000 (
1$
#765000
0#
#767200
0$
#767500
b10011001 '
1#
#770000
0#
#770625
b1110001 (
1$
#772500
b10011010 '
1#
#774050
0$
#775000
0#
#777475
b1110010 (
1$
#777500
b10011011 '
1#
#780000
0#
#780900
0$
#782500
b10011100 '
1#
#784325
b1110011 (
1$
#785000
0#
#787500
b10011101 '
1#
#787750
0$
#790000
0#
#791175
b1110100 (
1$
#792500
b10011110 '
1#
#794600
0$
#795000
0#
#797500
b10011111 '
1#
#798025
b1110101 (
1$
#800000
0#
#801450
0$
#802500
b10100000 '
1#
#804875
b1110110 (
1$
#805000
0#
#807500
b10100001 '
1#
#808300
0$
#810000
0#
#811725
b1110111 (
1$
#812500
b10100010 '
1#
#815000
0#
#815150
0$
#817500
b10100011 '
1#
#818575
b1111000 (
1$
#820000
0#
#822000
0$
#822500
b10100100 '
1#
#825000
0#
#825425
b1111001 (
1$
#827500
b10100101 '
1#
#828850
0$
#830000
0#
#832275
b1111010 (
1$
#832500
b10100110 '
1#
#835000
0#
#835700
0$
#837500
b10100111 '
1#
#839125
b1111011 (
1$
#840000
0#
#842500
b10101000 '
1#
#842550
0$
#845000
0#
#845975
b1111100 (
1$
#847500
b10101001 '
1#
#849400
0$
#850000
0#
#852500
b10101010 '
1#
#852825
b1111101 (
1$
#855000
0#
#856250
0$
#857500
b10101011 '
1#
#859675
b1111110 (
1$
#860000
0#
#862500
b10101100 '
1#
#863100
0$
#865000
0#
#866525
b1111111 (
1$
#867500
b10101101 '
1#
#869950
0$
#870000
0#
#872500
b10101110 '
1#
#873375
b10000000 (
1$
#875000
0#
#876800
0$
#877500
b10101111 '
1#
#880000
0#
#880225
b10000001 (
1$
#882500
b10110000 '
1#
#883650
0$
#885000
0#
#887075
b10000010 (
1$
#887500
b10110001 '
1#
#890000
0#
#890500
0$
#892500
b10110010 '
1#
#893925
b10000011 (
1$
#895000
0#
#897350
0$
#897500
b10110011 '
1#
#900000
0#
#900775
b10000100 (
1$
#902500
b10110100 '
1#
#904200
0$
#905000
0#
#907500
b10110101 '
1#
#907625
b10000101 (
1$
#910000
0#
#911050
0$
#912500
b10110110 '
1#
#914475
b10000110 (
1$
#915000
0#
#917500
b10110111 '
1#
#917900
0$
#920000
0#
#921325
b10000111 (
1$
#922500
b10111000 '
1#
#924750
0$
#925000
0#
#927500
b10111001 '
1#
#928175
b10001000 (
1$
#930000
0#
#931600
0$
#932500
b10111010 '
1#
#935000
0#
#935025
b10001001 (
1$
#937500
b10111011 '
1#
#938450
0$
#940000
0#
#941875
b10001010 (
1$
#942500
b10111100 '
1#
#945000
0#
#945300
0$
#947500
b10111101 '
1#
#948725
b10001011 (
1$
#950000
0#
#952150
0$
#952500
b10111110 '
1#
#955000
0#
#955575
b10001100 (
1$
#957500
b10111111 '
1#
#959000
0$
#960000
0#
#962425
b10001101 (
1$
#962500
b11000000 '
1#
#965000
0#
#965850
0$
#967500
b11000001 '
1#
#969275
b10001110 (
1$
#970000
0#
#972500
b11000010 '
1#
#972700
0$
#975000
0#
#976125
b10001111 (
1$
#977500
b11000011 '
1#
#979550
0$
#980000
0#
#982500
b11000100 '
1#
#982975
b10010000 (
1$
#985000
0#
#986400
0$
#987500
b11000101 '
1#
#989825
b10010001 (
1$
#990000
0#
#992500
b11000110 '
1#
#993250
0$
#995000
0#
#996675
b10010010 (
1$
#997500
b11000111 '
1#
#1000000
0#
#1000100
0$
#1002500
b11001000 '
1#
#1003525
b10010011 (
1$
#1005000
0#
#1006950
0$
#1007500
b11001001 '
1#
#1010000
0#
#1010375
b10010100 (
1$
#1012500
b11001010 '
1#
#1013800
0$
#1015000
0#
#1017225
b10010101 (
1$
#1017500
b11001011 '
1#
#1020000
0#
#1020650
0$
#1022500
b11001100 '
1#
#1024075
b10010110 (
1$
#1025000
0#
#1027500
b11001101 '
1#
0$
#1030000
0#
#1030925
b10010111 (
1$
#1032500
b11001110 '
1#
#1034350
0$
#1035000
0#
#1037500
b11001111 '
1#
#1037775
b10011000 (
1$
#1040000
0#
#1041200
0$
#1042500
b11010000 '
1#
#1044625
b10011001 (
1$
#1045000
0#
#1047500
b11010001 '
1#
#1048050
0$
#1050000
0#
#1051475
b10011010 (
1$
#1052500
b11010010 '
1#
#1054900
0$
#1055000
0#
#1057500
b11010011 '
1#
#1058325
b10011011 (
1$
#1060000
0#
#1061750
0$
#1062500
b11010100 '
1#
#1065000
0#
#1065175
b10011100 (
1$
#1067500
b11010101 '
1#
#1068600
0$
#1070000
0#
#1072025
b10011101 (
1$
#1072500
b11010110 '
1#
#1075000
0#
#1075450
0$
#1077500
b11010111 '
1#
#1078875
b10011110 (
1$
#1080000
0#
#1082300
0$
#1082500
b11011000 '
1#
#1085000
0#
#1085725
b10011111 (
1$
#1087500
b11011001 '
1#
#1089150
0$
#1090000
0#
#1092500
b11011010 '
1#
#1092575
b10100000 (
1$
#1095000
0#
#1096000
0$
#1097500
b11011011 '
1#
#1099425
b10100001 (
1$
#1100000
0#
#1102500
b11011100 '
1#
#1102850
0$
#1105000
0#
#1106275
b10100010 (
1$
#1107500
b11011101 '
1#
#1109700
0$
#1110000
0#
#1112500
b11011110 '
1#
#1113125
b10100011 (
1$
#1115000
0#
#1116550
0$
#1117500
b11011111 '
1#
#1119975
b10100100 (
1$
#1120000
0#
#1122500
b11100000 '
1#
#1123400
0$
#1125000
0#
#1126825
b10100101 (
1$
#1127500
b11100001 '
1#
#1130000
0#
#1130250
0$
#1132500
b11100010 '
1#
#1133675
b10100110 (
1$
#1135000
0#
#1137100
0$
#1137500
b11100011 '
1#
#1140000
0#
#1140525
b10100111 (
1$
#1142500
b11100100 '
1#
#1143950
0$
#1145000
0#
#1147375
b10101000 (
1$
#1147500
b11100101 '
1#
#1150000
0#
#1150800
0$
#1152500
b11100110 '
1#
#1154225
b10101001 (
1$
#1155000
0#
#1157500
b11100111 '
1#
#1157650
0$
#1160000
0#
#1161075
b10101010 (
1$
#1162500
b11101000 '
1#
#1164500
0$
#1165000
0#
#1167500
b11101001 '
1#
#1167925
b10101011 (
1$
#1170000
0#
#1171350
0$
#1172500
b11101010 '
1#
#1174775
b10101100 (
1$
#1175000
0#
#1177500
b11101011 '
1#
#1178200
0$
#1180000
0#
#1181625
b10101101 (
1$
#1182500
b11101100 '
1#
#1185000
0#
#1185050
0$
#1187500
b11101101 '
1#
#1188475
b10101110 (
1$
#1190000
0#
#1191900
0$
#1192500
b11101110 '
1#
#1195000
0#
#1195325
b10101111 (
1$
#1197500
b11101111 '
1#
#1198750
0$
#1200000
0#
#1202175
b10110000 (
1$
#1202500
b11110000 '
1#
#1205000
0#
#1205600
0$
#1207500
b11110001 '
1#
#1209025
b10110001 (
1$
#1210000
0#
#1212450
0$
#1212500
b11110010 '
1#
#1215000
0#
#1215875
b10110010 (
1$
#1217500
b11110011 '
1#
#1219300
0$
#1220000
0#
#1222500
b11110100 '
1#
#1222725
b10110011 (
1$
#1225000
0#
#1226150
0$
#1227500
b11110101 '
1#
#1229575
b10110100 (
1$
#1230000
0#
#1232500
b11110110 '
1#
#1233000
0$
#1235000
0#
#1236425
b10110101 (
1$
#1237500
b11110111 '
1#
#1239850
0$
#1240000
0#
#1242500
b11111000 '
1#
#1243275
b10110110 (
1$
#1245000
0#
#1246700
0$
#1247500
b11111001 '
1#
#1250000
0#
#1250125
b10110111 (
1$
#1252500
b11111010 '
1#
#1253550
0$
#1255000
0#
#1256975
b10111000 (
1$
#1257500
b11111011 '
1#
#1260000
0#
#1260400
0$
#1262500
b11111100 '
1#
#1263825
b10111001 (
1$
#1265000
0#
#1267250
0$
#1267500
b11111101 '
1#
#1270000
0#
#1270675
b10111010 (
1$
#1272500
b11111110 '
1#
#1274100
0$
#1275000
0#
#1277500
b11111111 '
1#
#1277525
b10111011 (
1$
#1280000
0#
#1280950
0$
#1282500
b100000000 '
1#
#1284375
b10111100 (
1$
#1285000
0#
#1287500
b100000001 '
1#
#1287800
0$
#1290000
0#
#1291225
b10111101 (
1$
#1292500
b100000010 '
1#
#1294650
0$
#1295000
0#
#1297500
b100000011 '
1#
#1298075
b10111110 (
1$
#1300000
0#
#1301500
0$
#1302500
b100000100 '
1#
#1304925
b10111111 (
1$
#1305000
0#
#1307500
b100000101 '
1#
#1308350
0$
#1310000
0#
#1311775
b11000000 (
1$
#1312500
b100000110 '
1#
#1315000
0#
#1315200
0$
#1317500
b100000111 '
1#
#1318625
b11000001 (
1$
#1320000
0#
#1322050
0$
#1322500
b100001000 '
1#
#1325000
0#
#1325475
b11000010 (
1$
#1327500
b100001001 '
1#
#1328900
0$
#1330000
0#
#1332325
b11000011 (
1$
#1332500
b100001010 '
1#
#1335000
0#
#1335750
0$
#1337500
b100001011 '
1#
#1339175
b11000100 (
1$
#1340000
0#
#1342500
b100001100 '
1#
#1342600
0$
#1345000
0#
#1346025
b11000101 (
1$
#1347500
b100001101 '
1#
#1349450
0$
#1350000
0#
#1352500
b100001110 '
1#
#1352875
b11000110 (
1$
#1355000
0#
#1356300
0$
#1357500
b100001111 '
1#
#1359725
b11000111 (
1$
#1360000
0#
#1362500
b100010000 '
1#
#1363150
0$
#1365000
0#
#1366575
b11001000 (
1$
#1367500
b100010001 '
1#
#1370000
0#
0$
#1372500
b100010010 '
1#
#1373425
b11001001 (
1$
#1375000
0#
#1376850
0$
#1377500
b100010011 '
1#
#1380000
0#
#1380275
b11001010 (
1$
#1382500
b100010100 '
1#
#1383700
0$
#1385000
0#
#1387125
b11001011 (
1$
#1387500
b100010101 '
1#
#1390000
0#
#1390550
0$
#1392500
b100010110 '
1#
#1393975
b11001100 (
1$
#1395000
0#
#1397400
0$
#1397500
b100010111 '
1#
#1400000
0#
#1400825
b11001101 (
1$
#1402500
b100011000 '
1#
#1404250
0$
#1405000
0#
#1407500
b100011001 '
1#
#1407675
b11001110 (
1$
#1410000
0#
#1411100
0$
#1412500
b100011010 '
1#
#1414525
b11001111 (
1$
#1415000
0#
#1417500
b100011011 '
1#
#1417950
0$
#1420000
0#
#1421375
b11010000 (
1$
#1422500
b100011100 '
1#
#1424800
0$
#1425000
0#
#1427500
b100011101 '
1#
#1428225
b11010001 (
1$
#1430000
0#
#1431650
0$
#1432500
b100011110 '
1#
#1435000
0#
#1435075
b11010010 (
1$
#1437500
b100011111 '
1#
#1438500
0$
#1440000
0#
#1441925
b11010011 (
1$
#1442500
b100100000 '
1#
#1445000
0#
#1445350
0$
#1447500
b100100001 '
1#
#1448775
b11010100 (
1$
#1450000
0#
#1452200
0$
#1452500
b100100010 '
1#
#1455000
0#
#1455625
b11010101 (
1$
#1457500
b100100011 '
1#
#1459050
0$
#1460000
0#
#1462475
b11010110 (
1$
#1462500
b100100100 '
1#
#1465000
0#
#1465900
0$
#1467500
b100100101 '
1#
#1469325
b11010111 (
1$
#1470000
0#
#1472500
b100100110 '
1#
#1472750
0$
#1475000
0#
#1476175
b11011000 (
1$
#1477500
b100100111 '
1#
#1479600
0$
#1480000
0#
#1482500
b100101000 '
1#
#1483025
b11011001 (
1$
#1485000
0#
#1486450
0$
#1487500
b100101001 '
1#
#1489875
b11011010 (
1$
#1490000
0#
#1492500
b100101010 '
1#
#1493300
0$
#1495000
0#
#1496725
b11011011 (
1$
#1497500
b100101011 '
1#
#1500000
0#
#1500150
0$
#1502500
b100101100 '
1#
#1503575
b11011100 (
1$
#1505000
0#
#1507000
0$
#1507500
b100101101 '
1#
#1510000
0#
#1510425
b11011101 (
1$
#1512500
b100101110 '
1#
#1513850
0$
#1515000
0#
#1517275
b11011110 (
1$
#1517500
b100101111 '
1#
#1520000
0#
#1520700
0$
#1522500
b100110000 '
1#
#1524125
b11011111 (
1$
#1525000
0#
#1527500
b100110001 '
1#
#1527550
0$
#1530000
0#
#1530975
b11100000 (
1$
#1532500
b100110010 '
1#
#1534400
0$
#1535000
0#
#1537500
b100110011 '
1#
#1537825
b11100001 (
1$
#1540000
0#
#1541250
0$
#1542500
b100110100 '
1#
#1544675
b11100010 (
1$
#1545000
0#
#1547500
b100110101 '
1#
#1548100
0$
#1550000
0#
#1551525
b11100011 (
1$
#1552500
b100110110 '
1#
#1554950
0$
#1555000
0#
#1557500
b100110111 '
1#
#1558375
b11100100 (
1$
#1560000
0#
#1561800
0$
#1562500
b100111000 '
1#
#1565000
0#
#1565225
b11100101 (
1$
#1567500
b100111001 '
1#
#1568650
0$
#1570000
0#
#1572075
b11100110 (
1$
#1572500
b100111010 '
1#
#1575000
0#
#1575500
0$
#1577500
b100111011 '
1#
#1578925
b11100111 (
1$
#1580000
0#
#1582350
0$
#1582500
b100111100 '
1#
#1585000
0#
#1585775
b11101000 (
1$
#1587500
b100111101 '
1#
#1589200
0$
#1590000
0#
#1592500
b100111110 '
1#
#1592625
b11101001 (
1$
#1595000
0#
#1596050
0$
#1597500
b100111111 '
1#
#1599475
b11101010 (
1$
#1600000
0#
#1602500
b101000000 '
1#
#1602900
0$
#1605000
0#
#1606325
b11101011 (
1$
#1607500
b101000001 '
1#
#1609750
0$
#1610000
0#
#1612500
b101000010 '
1#
#1613175
b11101100 (
1$
#1615000
0#
#1616600
0$
#1617500
b101000011 '
1#
#1620000
0#
#1620025
b11101101 (
1$
#1622500
b101000100 '
1#
#1623450
0$
#1625000
0#
#1626875
b11101110 (
1$
#1627500
b101000101 '
1#
#1630000
0#
#1630300
0$
#1632500
b101000110 '
1#
#1633725
b11101111 (
1$
#1635000
0#
#1637150
0$
#1637500
b101000111 '
1#
#1640000
0#
#1640575
b11110000 (
1$
#1642500
b101001000 '
1#
#1644000
0$
#1645000
0#
#1647425
b11110001 (
1$
#1647500
b101001001 '
1#
#1650000
0#
#1650850
0$
#1652500
b101001010 '
1#
#1654275
b11110010 (
1$
#1655000
0#
#1657500
b101001011 '
1#
#1657700
0$
#1660000
0#
#1661125
b11110011 (
1$
#1662500
b101001100 '
1#
#1664550
0$
#1665000
0#
#1667500
b101001101 '
1#
#1667975
b11110100 (
1$
#1670000
0#
#1671400
0$
#1672500
b101001110 '
1#
#1674825
b11110101 (
1$
#1675000
0#
#1677500
b101001111 '
1#
#1678250
0$
#1680000
0#
#1681675
b11110110 (
1$
#1682500
b101010000 '
1#
#1685000
0#
#1685100
0$
#1687500
b101010001 '
1#
#1688525
b11110111 (
1$
#1690000
0#
#1691950
0$
#1692500
b101010010 '
1#
#1695000
0#
#1695375
b11111000 (
1$
#1697500
b101010011 '
1#
#1698800
0$
#1700000
0#
#1702225
b11111001 (
1$
#1702500
b101010100 '
1#
#1705000
0#
#1705650
0$
#1707500
b101010101 '
1#
#1709075
b11111010 (
1$
#1710000
0#
#1712500
b101010110 '
1#
0$
#1715000
0#
#1715925
b11111011 (
1$
#1717500
b101010111 '
1#
#1719350
0$
#1720000
0#
#1722500
b101011000 '
1#
#1722775
b11111100 (
1$
#1725000
0#
#1726200
0$
#1727500
b101011001 '
1#
#1729625
b11111101 (
1$
#1730000
0#
#1732500
b101011010 '
1#
#1733050
0$
#1735000
0#
#1736475
b11111110 (
1$
#1737500
b101011011 '
1#
#1739900
0$
#1740000
0#
#1742500
b101011100 '
1#
#1743325
b11111111 (
1$
#1745000
0#
#1746750
0$
#1747500
b101011101 '
1#
#1750000
0#
#1750175
b100000000 (
1$
#1752500
b101011110 '
1#
#1753600
0$
#1755000
0#
#1757025
b100000001 (
1$
#1757500
b101011111 '
1#
#1760000
0#
#1760450
0$
#1762500
b101100000 '
1#
#1763875
b100000010 (
1$
#1765000
0#
#1767300
0$
#1767500
b101100001 '
1#
#1770000
0#
#1770725
b100000011 (
1$
#1772500
b101100010 '
1#
#1774150
0$
#1775000
0#
#1777500
b101100011 '
1#
#1777575
b100000100 (
1$
#1780000
0#
#1781000
0$
#1782500
b101100100 '
1#
#1784425
b100000101 (
1$
#1785000
0#
#1787500
b101100101 '
1#
#1787850
0$
#1790000
0#
#1791275
b100000110 (
1$
#1792500
b101100110 '
1#
#1794700
0$
#1795000
0#
#1797500
b101100111 '
1#
#1798125
b100000111 (
1$
#1800000
0#
#1801550
0$
#1802500
b101101000 '
1#
#1804975
b100001000 (
1$
#1805000
0#
#1807500
b101101001 '
1#
#1808400
0$
#1810000
0#
#1811825
b100001001 (
1$
#1812500
b101101010 '
1#
#1815000
0#
#1815250
0$
#1817500
b101101011 '
1#
#1818675
b100001010 (
1$
#1820000
0#
#1822100
0$
#1822500
b101101100 '
1#
#1825000
0#
#1825525
b100001011 (
1$
#1827500
b101101101 '
1#
#1828950
0$
#1830000
0#
#1832375
b100001100 (
1$
#1832500
b101101110 '
1#
#1835000
0#
#1835800
0$
#1837500
b101101111 '
1#
#1839225
b100001101 (
1$
#1840000
0#
#1842500
b101110000 '
1#
#1842650
0$
#1845000
0#
#1846075
b100001110 (
1$
#1847500
b101110001 '
1#
#1849500
0$
#1850000
0#
#1852500
b101110010 '
1#
#1852925
b100001111 (
1$
#1855000
0#
#1856350
0$
#1857500
b101110011 '
1#
#1859775
b100010000 (
1$
#1860000
0#
#1862500
b101110100 '
1#
#1863200
0$
#1865000
0#
#1866625
b100010001 (
1$
#1867500
b101110101 '
1#
#1870000
0#
#1870050
0$
