backend.v
// module testbench();

//     reg i_resetbAll;
//     reg i_clk;
//     reg i_sclk;
//     reg i_sdin;
//     reg i_vco_clk;

//     wire o_ready;
//     wire o_resetb1;
//     wire [1:0] o_gainA1;
//     wire o_resetb2;
//     wire [2:0] o_gainA2;
//     wire o_resetbvco;
    


//     initial begin
//         $monitor("%t %b %b %b %b %b %b ",$time,o_ready, o_resetb1, o_resetb2, o_gainA1, o_gainA2, o_resetbvco);
//     end

//     initial begin
//         $dumpfile("backend.vcd");
//         $dumpvars(0,testbench);
//     end
        
//     backend bk(i_resetbAll,
//                 i_clk,
//                 i_sclk,
//                 i_sdin,
//                 i_vco_clk,
//                 o_ready,
//                 o_resetb1,
//                 o_gainA1,
//                 o_resetb2,
//                 o_gainA2,
//                 o_resetbvco);

//     initial begin
//         i_clk = 0;
//         i_resetbAll = 1;
//         i_sclk = 0;
//         i_sdin = 0;
//         i_vco_clk = 0; 
//         #5 i_resetbAll = 0;
//         #15 i_resetbAll = 1;
//         #20 i_sdin = 1;
//         #30 i_sdin = 0;
//         #30 i_sdin = 0;
//         #30 i_sdin = 1;
//         #30 i_sdin = 1;
//         #30 i_sdin = 0;
//         #700 $finish;   
//     end 
//     always #15 i_sclk = ~i_sclk;
//     always #10 i_clk = ~i_clk; 
    
    



// endmodule


module backend (
    i_resetbAll,
    i_clk,
    i_sclk,
    i_sdin,
    i_vco_clk,
    o_ready,
    o_resetb1,
    o_gainA1,
    o_resetb2,
    o_gainA2,
    o_resetbvco
);
    input i_resetbAll;
    input i_clk;
    input i_sclk;
    input i_sdin;
    input i_vco_clk;

    output reg o_ready;
    output reg o_resetb1;
    output reg [1:0] o_gainA1;
    output reg o_resetb2;
    output reg [2:0] o_gainA2;
    output reg o_resetbvco;
    
    integer  i;
    reg [10:0]vco_freq;
    reg k;
    initial k = 0;
    

    // frequency_estimator fe(i_clk,i_vco_clk,i_resetbAll,vco_freq);
    initial vco_freq = 10'd0;
    // initial $monitor("%t %d",$time,vco_freq);
    always @(negedge(i_resetbAll)) begin
        o_ready = 0;
        o_resetb1 = 0;
        o_gainA1 = 2'd0;
        o_resetb2 = 0;
        o_gainA2 = 3'd0;
        o_resetbvco = 0;
        k = 0;
    end

    
    integer mainf = 0;
    integer vcof = 0;
    integer ans = 0;

    always @(posedge(i_resetbAll)) begin
        k = 1;
    end

    always @(posedge(i_clk) && k) begin
        mainf = mainf + 1;
        if(mainf==10000)begin
            @(posedge(i_vco_clk));
            vcof = vcof +1;
            ans = (vcof*200)/mainf;
            vco_freq = ans;
            $display("\ni_vco_frequency: %d\n",ans);
            k = 0;
            mainf = 0;
            vcof = 0;
            $finish;
        end
    end

    always @(posedge(i_vco_clk) && k) begin
        vcof = vcof + 1;
    end

    always @(posedge(i_resetbAll)) begin
        
        for(i=0;i<2;i=i+1)begin
            @(posedge(i_sclk));
            o_gainA1[i] = i_sdin;
        end


        for(i=0;i<3;i=i+1)begin
            @(posedge(i_sclk));
            o_gainA2[i] = i_sdin;
        end

        repeat(2)begin
            @(posedge(i_clk));
        end
        o_resetbvco = 1;

        repeat(10)begin
            @(posedge(i_clk));
        end
        o_resetb1 = 1;
        o_resetb2 = 1;
        repeat(10)begin
            @(posedge(i_clk));
        end
        o_ready = 1;
    end

    // always @(posedge(i_resetbAll)) begin
        
    // end



endmodule

FPGA_model.v
///////////////////////////////////////////////////////////////////////////////
/*FPGA model
 * Generates reset signal for the chip
 * Sends out progamming bits to the chip
*/
module FPGA_model(	i_resetbFPGA,
			i_ready,
			i_mainclk,
			o_resetbAll,
			o_sclk, 
			o_sdout);

//============================================================================
//Parameter declarations
parameter opcode_gainA1	= 2; //range: 0-3. Gain for amplifier 1
parameter opcode_gainA2	= 5; //range: 0-7. Gain for amplifier 2

//FPGA states
parameter sRESET 	= 0; //Reset all internal variables. Make o_resetbAll=0.
parameter sPROGRAM	= 1; //Send programming bits to chip.
parameter sIDLE		= 2; //Do nothing.
//===========================================================================
//Input output declarations
input i_resetbFPGA; 		//resets FPGA
input i_ready;			//Alerts FPGA that chip is programmed and ready
input i_mainclk;		//Main clock
output reg o_resetbAll;		//Reset for the chip
output reg o_sclk;		//Serial clock for communication
output reg o_sdout;		//Serial data out from FPGA (to chip)


//Internal wire, reg declarations
reg [1:0] FPGAstate;		//Holds the state of FPGA
reg [3:0] count;		//Used for controlling sclk generation and transmission of serial data
reg mainclkby2, mainclkby4, mainclkby8, mainclkby16; //Low frequency clocks derived from mainclk

//=============================================================
//BEHAVIORAL DESCRIPTION
//=============================================================
// Setting the FPGA state
always @ (posedge(i_mainclk) or negedge(i_resetbFPGA))
begin
	if(i_resetbFPGA == 0)
		FPGAstate <= sRESET;
	else
	begin
		case(FPGAstate)
		sRESET: FPGAstate <= sPROGRAM;
		sPROGRAM: 
		begin	
			if(count== 10)
				FPGAstate <= sIDLE;
			else
				FPGAstate <= sPROGRAM;
		end
		sIDLE: FPGAstate <=sIDLE;
		default: FPGAstate <= sIDLE;
		endcase
	end
end
//========================================================
/*resetbALL
 * resetbAll=0, when FPGA is reset. 
 * resetbAll=1 at all other times.
*/
always @(posedge(i_mainclk) or negedge(i_resetbFPGA))
begin
	if(i_resetbFPGA == 0)
		o_resetbAll <= 0;
	else
	begin
		if(FPGAstate == sRESET)
			o_resetbAll <= 0;
		else
			o_resetbAll <= 1;
	end
end
//==========================================================
/* Generation of low frequency clocks from mainclk using divide-by-2 method
*/
always @ (posedge(i_mainclk) or negedge(i_resetbFPGA))
begin
	if(i_resetbFPGA == 0)
		mainclkby2 <= 0;
	else
		mainclkby2 <= ~mainclkby2;
end

always @ (posedge(mainclkby2) or negedge(i_resetbFPGA))
begin
	if(i_resetbFPGA == 0)
		mainclkby4 <= 0;
	else
		mainclkby4 <= ~mainclkby4;
end

always @(posedge(mainclkby4) or negedge(i_resetbFPGA))
begin
	if(i_resetbFPGA == 0)
		mainclkby8 <= 0;
	else
		mainclkby8 <= ~mainclkby8;
end

always @(posedge(mainclkby8) or negedge(i_resetbFPGA))
begin
	if(i_resetbFPGA == 0)
		mainclkby16 <= 0;
	else
		mainclkby16 <= ~mainclkby16;
end
//==========================================================
/*count
 * used for the generation of sclk and selecting the data to be sent in through sdin
 */
always	@(posedge(mainclkby16) or negedge(i_resetbFPGA))
begin
	if(i_resetbFPGA == 0)
		count <= 0;
	else
	begin
		if(FPGAstate == sPROGRAM)
		begin
			if(count == 11)
				count <= count;
			else
				count <= count+1;
		end
		else
			count <= count;
	end
end
//=========================================================
/*sclk
 * sclk is a clock only when the FPGA is programming the chip.
 */
always @ (posedge(mainclkby16) or negedge(i_resetbFPGA))
begin
	if(i_resetbFPGA == 0)
		o_sclk <= 1;
	else
	begin
		if(FPGAstate == sPROGRAM)
		begin
			if (count >= 1 && count <= 10)
				o_sclk <= ~o_sclk;
			else
				o_sclk <= 1;
		end
		else
			o_sclk <= 1;
	end
end

//=========================================================
/*sdin
 *serial data out from FPGA
 */
always @ (negedge(o_sclk) or negedge(i_resetbFPGA))
begin
	if(i_resetbFPGA == 0)
		o_sdout <= 0;
	else
	begin
		if(FPGAstate == sPROGRAM)
		begin
			case(count)
			4'd2: o_sdout <= opcode_gainA1[0];
			4'd4: o_sdout <= opcode_gainA1[1];
			4'd6: o_sdout <= opcode_gainA2[0];
			4'd8: o_sdout <= opcode_gainA2[1];
			4'd10: o_sdout <= opcode_gainA2[2];
			default: o_sdout <= o_sdout;
			endcase
		end
		else
			o_sdout <= 0;
		
	end
end
//==========================================================
endmodule

backend_tb.v
// Testbanch module for the backend. This is has a module instantiation for
// the FPGA_model and the backend.
`timescale 1ns / 1ps
//==========================================================================
//Change the Verilog filenames approppriately.
`include "FPGA_model.v"
`include "backend.v"
//=========================================================================

module backend_tb();

reg resetbFPGA;
reg main_clk;

wire [1:0]gainA1 ; 
wire [2:0]gainA2 ;
wire resetbAll, resetb1, resetb2, resetbvco; 
wire vco_clk;
wire sclk, sdin;
wire ready;

initial begin
	$monitor("%t %b %b %b %b %b %b",$time,ready, resetb1, resetb2, gainA1, gainA2, resetbvco);
end

//==========================================================================
//FPGA model instantiation
FPGA_model   FPGA_obj(	.i_resetbFPGA (resetbFPGA),
			.i_ready (ready),
			.o_resetbAll (resetbAll),
			.i_mainclk (main_clk),
			.o_sclk (sclk), 
			.o_sdout (sdin));

// Backend instantiation 
backend backend_obj (	.i_resetbAll (resetbAll),
			.i_clk (main_clk),
			.i_sclk (sclk),
			.i_sdin (sdin),
			.i_vco_clk (vco_clk),
			.o_ready (ready),
			.o_resetb1 (resetb1),
			.o_gainA1 (gainA1),
			.o_resetb2 (resetb2),
			.o_gainA2 (gainA2),
			.o_resetbvco (resetbvco)
			);
//============================================================================
    initial begin
        $dumpfile("testbench.vcd");
        $dumpvars(0,backend_tb);
    end

//Test signal generation
initial
begin
	resetbFPGA <= 0;
	main_clk <= 0;
	
	#1 resetbFPGA <= 1;
	#2500 $finish;
end

//Generation of main_clk 
always #2.5 main_clk <= ~main_clk;
//============================================================================
endmodule

testbench.vcd
$date
	Tue Oct 25 17:32:02 2022
$end
$version
	Icarus Verilog
$end
$timescale
	1ps
$end
$scope module backend_tb $end
$var wire 1 ! sdin $end
$var wire 1 " sclk $end
$var wire 1 # resetbvco $end
$var wire 1 $ resetbAll $end
$var wire 1 % resetb2 $end
$var wire 1 & resetb1 $end
$var wire 1 ' ready $end
$var wire 3 ( gainA2 [2:0] $end
$var wire 2 ) gainA1 [1:0] $end
$var reg 1 * main_clk $end
$var reg 1 + resetbFPGA $end
$var reg 1 , vco_clk $end
$scope module FPGA_obj $end
$var wire 1 * i_mainclk $end
$var wire 1 + i_resetbFPGA $end
$var wire 1 ' i_ready $end
$var parameter 32 - opcode_gainA1 $end
$var parameter 32 . opcode_gainA2 $end
$var parameter 32 / sIDLE $end
$var parameter 32 0 sPROGRAM $end
$var parameter 32 1 sRESET $end
$var reg 2 2 FPGAstate [1:0] $end
$var reg 4 3 count [3:0] $end
$var reg 1 4 mainclkby16 $end
$var reg 1 5 mainclkby2 $end
$var reg 1 6 mainclkby4 $end
$var reg 1 7 mainclkby8 $end
$var reg 1 $ o_resetbAll $end
$var reg 1 " o_sclk $end
$var reg 1 ! o_sdout $end
$upscope $end
$scope module backend_obj $end
$var wire 1 * i_clk $end
$var wire 1 $ i_resetbAll $end
$var wire 1 " i_sclk $end
$var wire 1 ! i_sdin $end
$var wire 1 , i_vco_clk $end
$var reg 1 8 k $end
$var reg 2 9 o_gainA1 [1:0] $end
$var reg 3 : o_gainA2 [2:0] $end
$var reg 1 ' o_ready $end
$var reg 1 & o_resetb1 $end
$var reg 1 % o_resetb2 $end
$var reg 1 # o_resetbvco $end
$var reg 11 ; vco_freq [10:0] $end
$var integer 32 < ans [31:0] $end
$var integer 32 = i [31:0] $end
$var integer 32 > mainf [31:0] $end
$var integer 32 ? vcof [31:0] $end
$upscope $end
$upscope $end
$enddefinitions $end
$comment Show the parameter values. $end
$dumpall
b0 1
b1 0
b10 /
b111 .
b11 -
$end
#0
$dumpvars
b0 ?
b0 >
bx =
b0 <
b0 ;
b0 :
b0 9
08
07
06
05
04
b0 3
b0 2
0,
0+
0*
b0 )
b0 (
0'
0&
0%
0$
0#
1"
0!
$end
#1000
1+
#1250
1,
#2500
b1 3
14
17
16
15
b1 2
0,
1*
#3750
1,
#5000
0,
0*
#6250
1,
#7500
b1 >
18
b0 =
1$
05
0,
1*
#8750
b1 ?
1,
#10000
0,
0*
#11250
b10 ?
1,
#12500
06
15
b10 >
0,
1*
#13750
b11 ?
1,
#15000
0,
0*
#16250
b100 ?
1,
#17500
05
b11 >
0,
1*
#18750
b101 ?
1,
#20000
0,
0*
#21250
b110 ?
1,
#22500
07
16
15
b100 >
0,
1*
#23750
b111 ?
1,
#25000
0,
0*
#26250
b1000 ?
1,
#27500
05
b101 >
0,
1*
#28750
b1001 ?
1,
#30000
0,
0*
#31250
b1010 ?
1,
#32500
06
15
b110 >
0,
1*
#33750
b1011 ?
1,
#35000
0,
0*
#36250
b1100 ?
1,
#37500
05
b111 >
0,
1*
#38750
b1101 ?
1,
#40000
0,
0*
#41250
b1110 ?
1,
#42500
04
17
16
15
b1000 >
0,
1*
#43750
b1111 ?
1,
#45000
0,
0*
#46250
b10000 ?
1,
#47500
05
b1001 >
0,
1*
#48750
b10001 ?
1,
#50000
0,
0*
#51250
b10010 ?
1,
#52500
06
15
b1010 >
0,
1*
#53750
b10011 ?
1,
#55000
0,
0*
#56250
b10100 ?
1,
#57500
05
b1011 >
0,
1*
#58750
b10101 ?
1,
#60000
0,
0*
#61250
b10110 ?
1,
#62500
07
16
15
b1100 >
0,
1*
#63750
b10111 ?
1,
#65000
0,
0*
#66250
b11000 ?
1,
#67500
05
b1101 >
0,
1*
#68750
b11001 ?
1,
#70000
0,
0*
#71250
b11010 ?
1,
#72500
06
15
b1110 >
0,
1*
#73750
b11011 ?
1,
#75000
0,
0*
#76250
b11100 ?
1,
#77500
05
b1111 >
0,
1*
#78750
b11101 ?
1,
#80000
0,
0*
#81250
b11110 ?
1,
#82500
1!
b10 3
0"
14
17
16
15
b10000 >
0,
1*
#83750
b11111 ?
1,
#85000
0,
0*
#86250
b100000 ?
1,
#87500
05
b10001 >
0,
1*
#88750
b100001 ?
1,
#90000
0,
0*
#91250
b100010 ?
1,
#92500
06
15
b10010 >
0,
1*
#93750
b100011 ?
1,
#95000
0,
0*
#96250
b100100 ?
1,
#97500
05
b10011 >
0,
1*
#98750
b100101 ?
1,
#100000
0,
0*
#101250
b100110 ?
1,
#102500
07
16
15
b10100 >
0,
1*
#103750
b100111 ?
1,
#105000
0,
0*
#106250
b101000 ?
1,
#107500
05
b10101 >
0,
1*
#108750
b101001 ?
1,
#110000
0,
0*
#111250
b101010 ?
1,
#112500
06
15
b10110 >
0,
1*
#113750
b101011 ?
1,
#115000
0,
0*
#116250
b101100 ?
1,
#117500
05
b10111 >
0,
1*
#118750
b101101 ?
1,
#120000
0,
0*
#121250
b101110 ?
1,
#122500
04
17
16
15
b11000 >
0,
1*
#123750
b101111 ?
1,
#125000
0,
0*
#126250
b110000 ?
1,
#127500
05
b11001 >
0,
1*
#128750
b110001 ?
1,
#130000
0,
0*
#131250
b110010 ?
1,
#132500
06
15
b11010 >
0,
1*
#133750
b110011 ?
1,
#135000
0,
0*
#136250
b110100 ?
1,
#137500
05
b11011 >
0,
1*
#138750
b110101 ?
1,
#140000
0,
0*
#141250
b110110 ?
1,
#142500
07
16
15
b11100 >
0,
1*
#143750
b110111 ?
1,
#145000
0,
0*
#146250
b111000 ?
1,
#147500
05
b11101 >
0,
1*
#148750
b111001 ?
1,
#150000
0,
0*
#151250
b111010 ?
1,
#152500
06
15
b11110 >
0,
1*
#153750
b111011 ?
1,
#155000
0,
0*
#156250
b111100 ?
1,
#157500
05
b11111 >
0,
1*
#158750
b111101 ?
1,
#160000
0,
0*
#161250
b111110 ?
1,
#162500
b1 =
b1 )
b1 9
1"
b11 3
14
17
16
15
b100000 >
0,
1*
#163750
b111111 ?
1,
#165000
0,
0*
#166250
b1000000 ?
1,
#167500
05
b100001 >
0,
1*
#168750
b1000001 ?
1,
#170000
0,
0*
#171250
b1000010 ?
1,
#172500
06
15
b100010 >
0,
1*
#173750
b1000011 ?
1,
#175000
0,
0*
#176250
b1000100 ?
1,
#177500
05
b100011 >
0,
1*
#178750
b1000101 ?
1,
#180000
0,
0*
#181250
b1000110 ?
1,
#182500
07
16
15
b100100 >
0,
1*
#183750
b1000111 ?
1,
#185000
0,
0*
#186250
b1001000 ?
1,
#187500
05
b100101 >
0,
1*
#188750
b1001001 ?
1,
#190000
0,
0*
#191250
b1001010 ?
1,
#192500
06
15
b100110 >
0,
1*
#193750
b1001011 ?
1,
#195000
0,
0*
#196250
b1001100 ?
1,
#197500
05
b100111 >
0,
1*
#198750
b1001101 ?
1,
#200000
0,
0*
#201250
b1001110 ?
1,
#202500
04
17
16
15
b101000 >
0,
1*
#203750
b1001111 ?
1,
#205000
0,
0*
#206250
b1010000 ?
1,
#207500
05
b101001 >
0,
1*
#208750
b1010001 ?
1,
#210000
0,
0*
#211250
b1010010 ?
1,
#212500
06
15
b101010 >
0,
1*
#213750
b1010011 ?
1,
#215000
0,
0*
#216250
b1010100 ?
1,
#217500
05
b101011 >
0,
1*
#218750
b1010101 ?
1,
#220000
0,
0*
#221250
b1010110 ?
1,
#222500
07
16
15
b101100 >
0,
1*
#223750
b1010111 ?
1,
#225000
0,
0*
#226250
b1011000 ?
1,
#227500
05
b101101 >
0,
1*
#228750
b1011001 ?
1,
#230000
0,
0*
#231250
b1011010 ?
1,
#232500
06
15
b101110 >
0,
1*
#233750
b1011011 ?
1,
#235000
0,
0*
#236250
b1011100 ?
1,
#237500
05
b101111 >
0,
1*
#238750
b1011101 ?
1,
#240000
0,
0*
#241250
b1011110 ?
1,
#242500
b100 3
0"
14
17
16
15
b110000 >
0,
1*
#243750
b1011111 ?
1,
#245000
0,
0*
#246250
b1100000 ?
1,
#247500
05
b110001 >
0,
1*
#248750
b1100001 ?
1,
#250000
0,
0*
#251250
b1100010 ?
1,
#252500
06
15
b110010 >
0,
1*
#253750
b1100011 ?
1,
#255000
0,
0*
#256250
b1100100 ?
1,
#257500
05
b110011 >
0,
1*
#258750
b1100101 ?
1,
#260000
0,
0*
#261250
b1100110 ?
1,
#262500
07
16
15
b110100 >
0,
1*
#263750
b1100111 ?
1,
#265000
0,
0*
#266250
b1101000 ?
1,
#267500
05
b110101 >
0,
1*
#268750
b1101001 ?
1,
#270000
0,
0*
#271250
b1101010 ?
1,
#272500
06
15
b110110 >
0,
1*
#273750
b1101011 ?
1,
#275000
0,
0*
#276250
b1101100 ?
1,
#277500
05
b110111 >
0,
1*
#278750
b1101101 ?
1,
#280000
0,
0*
#281250
b1101110 ?
1,
#282500
04
17
16
15
b111000 >
0,
1*
#283750
b1101111 ?
1,
#285000
0,
0*
#286250
b1110000 ?
1,
#287500
05
b111001 >
0,
1*
#288750
b1110001 ?
1,
#290000
0,
0*
#291250
b1110010 ?
1,
#292500
06
15
b111010 >
0,
1*
#293750
b1110011 ?
1,
#295000
0,
0*
#296250
b1110100 ?
1,
#297500
05
b111011 >
0,
1*
#298750
b1110101 ?
1,
#300000
0,
0*
#301250
b1110110 ?
1,
#302500
07
16
15
b111100 >
0,
1*
#303750
b1110111 ?
1,
#305000
0,
0*
#306250
b1111000 ?
1,
#307500
05
b111101 >
0,
1*
#308750
b1111001 ?
1,
#310000
0,
0*
#311250
b1111010 ?
1,
#312500
06
15
b111110 >
0,
1*
#313750
b1111011 ?
1,
#315000
0,
0*
#316250
b1111100 ?
1,
#317500
05
b111111 >
0,
1*
#318750
b1111101 ?
1,
#320000
0,
0*
#321250
b1111110 ?
1,
#322500
b0 =
b11 )
b11 9
1"
b101 3
14
17
16
15
b1000000 >
0,
1*
#323750
b1111111 ?
1,
#325000
0,
0*
#326250
b10000000 ?
1,
#327500
05
b1000001 >
0,
1*
#328750
b10000001 ?
1,
#330000
0,
0*
#331250
b10000010 ?
1,
#332500
06
15
b1000010 >
0,
1*
#333750
b10000011 ?
1,
#335000
0,
0*
#336250
b10000100 ?
1,
#337500
05
b1000011 >
0,
1*
#338750
b10000101 ?
1,
#340000
0,
0*
#341250
b10000110 ?
1,
#342500
07
16
15
b1000100 >
0,
1*
#343750
b10000111 ?
1,
#345000
0,
0*
#346250
b10001000 ?
1,
#347500
05
b1000101 >
0,
1*
#348750
b10001001 ?
1,
#350000
0,
0*
#351250
b10001010 ?
1,
#352500
06
15
b1000110 >
0,
1*
#353750
b10001011 ?
1,
#355000
0,
0*
#356250
b10001100 ?
1,
#357500
05
b1000111 >
0,
1*
#358750
b10001101 ?
1,
#360000
0,
0*
#361250
b10001110 ?
1,
#362500
04
17
16
15
b1001000 >
0,
1*
#363750
b10001111 ?
1,
#365000
0,
0*
#366250
b10010000 ?
1,
#367500
05
b1001001 >
0,
1*
#368750
b10010001 ?
1,
#370000
0,
0*
#371250
b10010010 ?
1,
#372500
06
15
b1001010 >
0,
1*
#373750
b10010011 ?
1,
#375000
0,
0*
#376250
b10010100 ?
1,
#377500
05
b1001011 >
0,
1*
#378750
b10010101 ?
1,
#380000
0,
0*
#381250
b10010110 ?
1,
#382500
07
16
15
b1001100 >
0,
1*
#383750
b10010111 ?
1,
#385000
0,
0*
#386250
b10011000 ?
1,
#387500
05
b1001101 >
0,
1*
#388750
b10011001 ?
1,
#390000
0,
0*
#391250
b10011010 ?
1,
#392500
06
15
b1001110 >
0,
1*
#393750
b10011011 ?
1,
#395000
0,
0*
#396250
b10011100 ?
1,
#397500
05
b1001111 >
0,
1*
#398750
b10011101 ?
1,
#400000
0,
0*
#401250
b10011110 ?
1,
#402500
b110 3
0"
14
17
16
15
b1010000 >
0,
1*
#403750
b10011111 ?
1,
#405000
0,
0*
#406250
b10100000 ?
1,
#407500
05
b1010001 >
0,
1*
#408750
b10100001 ?
1,
#410000
0,
0*
#411250
b10100010 ?
1,
#412500
06
15
b1010010 >
0,
1*
#413750
b10100011 ?
1,
#415000
0,
0*
#416250
b10100100 ?
1,
#417500
05
b1010011 >
0,
1*
#418750
b10100101 ?
1,
#420000
0,
0*
#421250
b10100110 ?
1,
#422500
07
16
15
b1010100 >
0,
1*
#423750
b10100111 ?
1,
#425000
0,
0*
#426250
b10101000 ?
1,
#427500
05
b1010101 >
0,
1*
#428750
b10101001 ?
1,
#430000
0,
0*
#431250
b10101010 ?
1,
#432500
06
15
b1010110 >
0,
1*
#433750
b10101011 ?
1,
#435000
0,
0*
#436250
b10101100 ?
1,
#437500
05
b1010111 >
0,
1*
#438750
b10101101 ?
1,
#440000
0,
0*
#441250
b10101110 ?
1,
#442500
04
17
16
15
b1011000 >
0,
1*
#443750
b10101111 ?
1,
#445000
0,
0*
#446250
b10110000 ?
1,
#447500
05
b1011001 >
0,
1*
#448750
b10110001 ?
1,
#450000
0,
0*
#451250
b10110010 ?
1,
#452500
06
15
b1011010 >
0,
1*
#453750
b10110011 ?
1,
#455000
0,
0*
#456250
b10110100 ?
1,
#457500
05
b1011011 >
0,
1*
#458750
b10110101 ?
1,
#460000
0,
0*
#461250
b10110110 ?
1,
#462500
07
16
15
b1011100 >
0,
1*
#463750
b10110111 ?
1,
#465000
0,
0*
#466250
b10111000 ?
1,
#467500
05
b1011101 >
0,
1*
#468750
b10111001 ?
1,
#470000
0,
0*
#471250
b10111010 ?
1,
#472500
06
15
b1011110 >
0,
1*
#473750
b10111011 ?
1,
#475000
0,
0*
#476250
b10111100 ?
1,
#477500
05
b1011111 >
0,
1*
#478750
b10111101 ?
1,
#480000
0,
0*
#481250
b10111110 ?
1,
#482500
b1 =
b1 (
b1 :
1"
b111 3
14
17
16
15
b1100000 >
0,
1*
#483750
b10111111 ?
1,
#485000
0,
0*
#486250
b11000000 ?
1,
#487500
05
b1100001 >
0,
1*
#488750
b11000001 ?
1,
#490000
0,
0*
#491250
b11000010 ?
1,
#492500
06
15
b1100010 >
0,
1*
#493750
b11000011 ?
1,
#495000
0,
0*
#496250
b11000100 ?
1,
#497500
05
b1100011 >
0,
1*
#498750
b11000101 ?
1,
#500000
0,
0*
#501250
b11000110 ?
1,
#502500
07
16
15
b1100100 >
0,
1*
#503750
b11000111 ?
1,
#505000
0,
0*
#506250
b11001000 ?
1,
#507500
05
b1100101 >
0,
1*
#508750
b11001001 ?
1,
#510000
0,
0*
#511250
b11001010 ?
1,
#512500
06
15
b1100110 >
0,
1*
#513750
b11001011 ?
1,
#515000
0,
0*
#516250
b11001100 ?
1,
#517500
05
b1100111 >
0,
1*
#518750
b11001101 ?
1,
#520000
0,
0*
#521250
b11001110 ?
1,
#522500
04
17
16
15
b1101000 >
0,
1*
#523750
b11001111 ?
1,
#525000
0,
0*
#526250
b11010000 ?
1,
#527500
05
b1101001 >
0,
1*
#528750
b11010001 ?
1,
#530000
0,
0*
#531250
b11010010 ?
1,
#532500
06
15
b1101010 >
0,
1*
#533750
b11010011 ?
1,
#535000
0,
0*
#536250
b11010100 ?
1,
#537500
05
b1101011 >
0,
1*
#538750
b11010101 ?
1,
#540000
0,
0*
#541250
b11010110 ?
1,
#542500
07
16
15
b1101100 >
0,
1*
#543750
b11010111 ?
1,
#545000
0,
0*
#546250
b11011000 ?
1,
#547500
05
b1101101 >
0,
1*
#548750
b11011001 ?
1,
#550000
0,
0*
#551250
b11011010 ?
1,
#552500
06
15
b1101110 >
0,
1*
#553750
b11011011 ?
1,
#555000
0,
0*
#556250
b11011100 ?
1,
#557500
05
b1101111 >
0,
1*
#558750
b11011101 ?
1,
#560000
0,
0*
#561250
b11011110 ?
1,
#562500
b1000 3
0"
14
17
16
15
b1110000 >
0,
1*
#563750
b11011111 ?
1,
#565000
0,
0*
#566250
b11100000 ?
1,
#567500
05
b1110001 >
0,
1*
#568750
b11100001 ?
1,
#570000
0,
0*
#571250
b11100010 ?
1,
#572500
06
15
b1110010 >
0,
1*
#573750
b11100011 ?
1,
#575000
0,
0*
#576250
b11100100 ?
1,
#577500
05
b1110011 >
0,
1*
#578750
b11100101 ?
1,
#580000
0,
0*
#581250
b11100110 ?
1,
#582500
07
16
15
b1110100 >
0,
1*
#583750
b11100111 ?
1,
#585000
0,
0*
#586250
b11101000 ?
1,
#587500
05
b1110101 >
0,
1*
#588750
b11101001 ?
1,
#590000
0,
0*
#591250
b11101010 ?
1,
#592500
06
15
b1110110 >
0,
1*
#593750
b11101011 ?
1,
#595000
0,
0*
#596250
b11101100 ?
1,
#597500
05
b1110111 >
0,
1*
#598750
b11101101 ?
1,
#600000
0,
0*
#601250
b11101110 ?
1,
#602500
04
17
16
15
b1111000 >
0,
1*
#603750
b11101111 ?
1,
#605000
0,
0*
#606250
b11110000 ?
1,
#607500
05
b1111001 >
0,
1*
#608750
b11110001 ?
1,
#610000
0,
0*
#611250
b11110010 ?
1,
#612500
06
15
b1111010 >
0,
1*
#613750
b11110011 ?
1,
#615000
0,
0*
#616250
b11110100 ?
1,
#617500
05
b1111011 >
0,
1*
#618750
b11110101 ?
1,
#620000
0,
0*
#621250
b11110110 ?
1,
#622500
07
16
15
b1111100 >
0,
1*
#623750
b11110111 ?
1,
#625000
0,
0*
#626250
b11111000 ?
1,
#627500
05
b1111101 >
0,
1*
#628750
b11111001 ?
1,
#630000
0,
0*
#631250
b11111010 ?
1,
#632500
06
15
b1111110 >
0,
1*
#633750
b11111011 ?
1,
#635000
0,
0*
#636250
b11111100 ?
1,
#637500
05
b1111111 >
0,
1*
#638750
b11111101 ?
1,
#640000
0,
0*
#641250
b11111110 ?
1,
#642500
b10 =
b11 (
b11 :
1"
b1001 3
14
17
16
15
b10000000 >
0,
1*
#643750
b11111111 ?
1,
#645000
0,
0*
#646250
b100000000 ?
1,
#647500
05
b10000001 >
0,
1*
#648750
b100000001 ?
1,
#650000
0,
0*
#651250
b100000010 ?
1,
#652500
06
15
b10000010 >
0,
1*
#653750
b100000011 ?
1,
#655000
0,
0*
#656250
b100000100 ?
1,
#657500
05
b10000011 >
0,
1*
#658750
b100000101 ?
1,
#660000
0,
0*
#661250
b100000110 ?
1,
#662500
07
16
15
b10000100 >
0,
1*
#663750
b100000111 ?
1,
#665000
0,
0*
#666250
b100001000 ?
1,
#667500
05
b10000101 >
0,
1*
#668750
b100001001 ?
1,
#670000
0,
0*
#671250
b100001010 ?
1,
#672500
06
15
b10000110 >
0,
1*
#673750
b100001011 ?
1,
#675000
0,
0*
#676250
b100001100 ?
1,
#677500
05
b10000111 >
0,
1*
#678750
b100001101 ?
1,
#680000
0,
0*
#681250
b100001110 ?
1,
#682500
04
17
16
15
b10001000 >
0,
1*
#683750
b100001111 ?
1,
#685000
0,
0*
#686250
b100010000 ?
1,
#687500
05
b10001001 >
0,
1*
#688750
b100010001 ?
1,
#690000
0,
0*
#691250
b100010010 ?
1,
#692500
06
15
b10001010 >
0,
1*
#693750
b100010011 ?
1,
#695000
0,
0*
#696250
b100010100 ?
1,
#697500
05
b10001011 >
0,
1*
#698750
b100010101 ?
1,
#700000
0,
0*
#701250
b100010110 ?
1,
#702500
07
16
15
b10001100 >
0,
1*
#703750
b100010111 ?
1,
#705000
0,
0*
#706250
b100011000 ?
1,
#707500
05
b10001101 >
0,
1*
#708750
b100011001 ?
1,
#710000
0,
0*
#711250
b100011010 ?
1,
#712500
06
15
b10001110 >
0,
1*
#713750
b100011011 ?
1,
#715000
0,
0*
#716250
b100011100 ?
1,
#717500
05
b10001111 >
0,
1*
#718750
b100011101 ?
1,
#720000
0,
0*
#721250
b100011110 ?
1,
#722500
b1010 3
0"
14
17
16
15
b10010000 >
0,
1*
#723750
b100011111 ?
1,
#725000
0,
0*
#726250
b100100000 ?
1,
#727500
b10 2
05
b10010001 >
0,
1*
#728750
b100100001 ?
1,
#730000
0,
0*
#731250
b100100010 ?
1,
#732500
06
15
b10010010 >
0,
1*
#733750
b100100011 ?
1,
#735000
0,
0*
#736250
b100100100 ?
1,
#737500
05
b10010011 >
0,
1*
#738750
b100100101 ?
1,
#740000
0,
0*
#741250
b100100110 ?
1,
#742500
07
16
15
b10010100 >
0,
1*
#743750
b100100111 ?
1,
#745000
0,
0*
#746250
b100101000 ?
1,
#747500
05
b10010101 >
0,
1*
#748750
b100101001 ?
1,
#750000
0,
0*
#751250
b100101010 ?
1,
#752500
06
15
b10010110 >
0,
1*
#753750
b100101011 ?
1,
#755000
0,
0*
#756250
b100101100 ?
1,
#757500
05
b10010111 >
0,
1*
#758750
b100101101 ?
1,
#760000
0,
0*
#761250
b100101110 ?
1,
#762500
04
17
16
15
b10011000 >
0,
1*
#763750
b100101111 ?
1,
#765000
0,
0*
#766250
b100110000 ?
1,
#767500
05
b10011001 >
0,
1*
