backend.v
// module testbench();

//     reg i_resetbAll;
//     reg i_clk;
//     reg i_sclk;
//     reg i_sdin;
//     reg i_vco_clk;

//     wire o_ready;
//     wire o_resetb1;
//     wire [1:0] o_gainA1;
//     wire o_resetb2;
//     wire [2:0] o_gainA2;
//     wire o_resetbvco;
    


//     initial begin
//         $monitor("%t %b %b %b %b %b %b ",$time,o_ready, o_resetb1, o_resetb2, o_gainA1, o_gainA2, o_resetbvco);
//     end

//     initial begin
//         $dumpfile("backend.vcd");
//         $dumpvars(0,testbench);
//     end
        
//     backend bk(i_resetbAll,
//                 i_clk,
//                 i_sclk,
//                 i_sdin,
//                 i_vco_clk,
//                 o_ready,
//                 o_resetb1,
//                 o_gainA1,
//                 o_resetb2,
//                 o_gainA2,
//                 o_resetbvco);

//     initial begin
//         i_clk = 0;
//         i_resetbAll = 1;
//         i_sclk = 0;
//         i_sdin = 0;
//         i_vco_clk = 0; 
//         #5 i_resetbAll = 0;
//         #15 i_resetbAll = 1;
//         #20 i_sdin = 1;
//         #30 i_sdin = 0;
//         #30 i_sdin = 0;
//         #30 i_sdin = 1;
//         #30 i_sdin = 1;
//         #30 i_sdin = 0;
//         #700 $finish;   
//     end 
//     always #15 i_sclk = ~i_sclk;
//     always #10 i_clk = ~i_clk; 
    
    



// endmodule


module backend (
    i_resetbAll,
    i_clk,
    i_sclk,
    i_sdin,
    i_vco_clk,
    o_ready,
    o_resetb1,
    o_gainA1,
    o_resetb2,
    o_gainA2,
    o_resetbvco
);
    input i_resetbAll;
    input i_clk;
    input i_sclk;
    input i_sdin;
    input i_vco_clk;

    output reg o_ready;
    output reg o_resetb1;
    output reg [1:0] o_gainA1;
    output reg o_resetb2;
    output reg [2:0] o_gainA2;
    output reg o_resetbvco;
    
    integer  i;
    reg [10:0]vco_freq;
    reg k;
    initial k = 0;
    

    // frequency_estimator fe(i_clk,i_vco_clk,i_resetbAll,vco_freq);
    initial vco_freq = 10'd0;
    // initial $monitor("%t %d",$time,vco_freq);
    always @(negedge(i_resetbAll)) begin
        o_ready = 0;
        o_resetb1 = 0;
        o_gainA1 = 2'd0;
        o_resetb2 = 0;
        o_gainA2 = 3'd0;
        o_resetbvco = 0;
        vco_freq = 10'd0;
        k = 0;
    end

    
    integer mainf = 0;
    integer vcof = 0;
    integer ans = 0;

    always @(posedge(i_resetbAll)) begin
        k = 1;
    end

    always @(posedge(i_clk) && k) begin
        mainf = mainf + 1;
        if(mainf==10000)begin
            @(posedge(i_vco_clk));
            vcof = vcof +1;
            ans = (vcof*200)/mainf;
            vco_freq = ans;
            $display("\ni_vco_frequency: %d\n",ans);
            k = 0;
            mainf = 0;
            vcof = 0;
            $finish;
        end
    end

    always @(posedge(i_vco_clk) && k) begin
        vcof = vcof + 1;
    end

    always @(posedge(i_resetbAll)) begin
        
        for(i=0;i<2;i=i+1)begin
            @(posedge(i_sclk));
            o_gainA1[i] = i_sdin;
        end


        for(i=0;i<3;i=i+1)begin
            @(posedge(i_sclk));
            o_gainA2[i] = i_sdin;
        end

        repeat(2)begin
            @(posedge(i_clk));
        end
        o_resetbvco = 1;

        repeat(10)begin
            @(posedge(i_clk));
        end
        o_resetb1 = 1;
        o_resetb2 = 1;
        repeat(10)begin
            @(posedge(i_clk));
        end
        o_ready = 1;
    end

    // always @(posedge(i_resetbAll)) begin
        
    // end



endmodule

FPGA_model.v
///////////////////////////////////////////////////////////////////////////////
/*FPGA model
 * Generates reset signal for the chip
 * Sends out progamming bits to the chip
*/
module FPGA_model(	i_resetbFPGA,
			i_ready,
			i_mainclk,
			o_resetbAll,
			o_sclk, 
			o_sdout);

//============================================================================
//Parameter declarations
parameter opcode_gainA1	= 2; //range: 0-3. Gain for amplifier 1
parameter opcode_gainA2	= 5; //range: 0-7. Gain for amplifier 2

//FPGA states
parameter sRESET 	= 0; //Reset all internal variables. Make o_resetbAll=0.
parameter sPROGRAM	= 1; //Send programming bits to chip.
parameter sIDLE		= 2; //Do nothing.
//===========================================================================
//Input output declarations
input i_resetbFPGA; 		//resets FPGA
input i_ready;			//Alerts FPGA that chip is programmed and ready
input i_mainclk;		//Main clock
output reg o_resetbAll;		//Reset for the chip
output reg o_sclk;		//Serial clock for communication
output reg o_sdout;		//Serial data out from FPGA (to chip)


//Internal wire, reg declarations
reg [1:0] FPGAstate;		//Holds the state of FPGA
reg [3:0] count;		//Used for controlling sclk generation and transmission of serial data
reg mainclkby2, mainclkby4, mainclkby8, mainclkby16; //Low frequency clocks derived from mainclk

//=============================================================
//BEHAVIORAL DESCRIPTION
//=============================================================
// Setting the FPGA state
always @ (posedge(i_mainclk) or negedge(i_resetbFPGA))
begin
	if(i_resetbFPGA == 0)
		FPGAstate <= sRESET;
	else
	begin
		case(FPGAstate)
		sRESET: FPGAstate <= sPROGRAM;
		sPROGRAM: 
		begin	
			if(count== 10)
				FPGAstate <= sIDLE;
			else
				FPGAstate <= sPROGRAM;
		end
		sIDLE: FPGAstate <=sIDLE;
		default: FPGAstate <= sIDLE;
		endcase
	end
end
//========================================================
/*resetbALL
 * resetbAll=0, when FPGA is reset. 
 * resetbAll=1 at all other times.
*/
always @(posedge(i_mainclk) or negedge(i_resetbFPGA))
begin
	if(i_resetbFPGA == 0)
		o_resetbAll <= 0;
	else
	begin
		if(FPGAstate == sRESET)
			o_resetbAll <= 0;
		else
			o_resetbAll <= 1;
	end
end
//==========================================================
/* Generation of low frequency clocks from mainclk using divide-by-2 method
*/
always @ (posedge(i_mainclk) or negedge(i_resetbFPGA))
begin
	if(i_resetbFPGA == 0)
		mainclkby2 <= 0;
	else
		mainclkby2 <= ~mainclkby2;
end

always @ (posedge(mainclkby2) or negedge(i_resetbFPGA))
begin
	if(i_resetbFPGA == 0)
		mainclkby4 <= 0;
	else
		mainclkby4 <= ~mainclkby4;
end

always @(posedge(mainclkby4) or negedge(i_resetbFPGA))
begin
	if(i_resetbFPGA == 0)
		mainclkby8 <= 0;
	else
		mainclkby8 <= ~mainclkby8;
end

always @(posedge(mainclkby8) or negedge(i_resetbFPGA))
begin
	if(i_resetbFPGA == 0)
		mainclkby16 <= 0;
	else
		mainclkby16 <= ~mainclkby16;
end
//==========================================================
/*count
 * used for the generation of sclk and selecting the data to be sent in through sdin
 */
always	@(posedge(mainclkby16) or negedge(i_resetbFPGA))
begin
	if(i_resetbFPGA == 0)
		count <= 0;
	else
	begin
		if(FPGAstate == sPROGRAM)
		begin
			if(count == 11)
				count <= count;
			else
				count <= count+1;
		end
		else
			count <= count;
	end
end
//=========================================================
/*sclk
 * sclk is a clock only when the FPGA is programming the chip.
 */
always @ (posedge(mainclkby16) or negedge(i_resetbFPGA))
begin
	if(i_resetbFPGA == 0)
		o_sclk <= 1;
	else
	begin
		if(FPGAstate == sPROGRAM)
		begin
			if (count >= 1 && count <= 10)
				o_sclk <= ~o_sclk;
			else
				o_sclk <= 1;
		end
		else
			o_sclk <= 1;
	end
end

//=========================================================
/*sdin
 *serial data out from FPGA
 */
always @ (negedge(o_sclk) or negedge(i_resetbFPGA))
begin
	if(i_resetbFPGA == 0)
		o_sdout <= 0;
	else
	begin
		if(FPGAstate == sPROGRAM)
		begin
			case(count)
			4'd2: o_sdout <= opcode_gainA1[0];
			4'd4: o_sdout <= opcode_gainA1[1];
			4'd6: o_sdout <= opcode_gainA2[0];
			4'd8: o_sdout <= opcode_gainA2[1];
			4'd10: o_sdout <= opcode_gainA2[2];
			default: o_sdout <= o_sdout;
			endcase
		end
		else
			o_sdout <= 0;
		
	end
end
//==========================================================
endmodule

backend_tb.v
// Testbanch module for the backend. This is has a module instantiation for
// the FPGA_model and the backend.
`timescale 1ns / 1ps
//==========================================================================
//Change the Verilog filenames approppriately.
`include "FPGA_model.v"
`include "backend.v"
//=========================================================================

module backend_tb();

reg resetbFPGA;
reg main_clk;

wire [1:0]gainA1 ; 
wire [2:0]gainA2 ;
wire resetbAll, resetb1, resetb2, resetbvco; 
reg vco_clk;
wire sclk, sdin;
wire ready;

initial begin
	$monitor("%t %b %b %b %b %b %b",$time,ready, resetb1, resetb2, gainA1, gainA2, resetbvco);
end

//==========================================================================
//FPGA model instantiation
FPGA_model   FPGA_obj(	.i_resetbFPGA (resetbFPGA),
			.i_ready (ready),
			.o_resetbAll (resetbAll),
			.i_mainclk (main_clk),
			.o_sclk (sclk), 
			.o_sdout (sdin));

// Backend instantiation 
backend backend_obj (	.i_resetbAll (resetbAll),
			.i_clk (main_clk),
			.i_sclk (sclk),
			.i_sdin (sdin),
			.i_vco_clk (vco_clk),
			.o_ready (ready),
			.o_resetb1 (resetb1),
			.o_gainA1 (gainA1),
			.o_resetb2 (resetb2),
			.o_gainA2 (gainA2),
			.o_resetbvco (resetbvco)
			);
//============================================================================
    initial begin
        $dumpfile("testbench.vcd");
        $dumpvars(0,backend_tb);
    end

//Test signal generation
initial
begin
	resetbFPGA <= 0;
	main_clk <= 0;
	vco_clk <= 0;
	#1 resetbFPGA <= 1;
	// #10000 $finish;
end

//Generation of main_clk 
always #2.5 main_clk <= ~main_clk;
always #0.555 vco_clk <= ~vco_clk;
//============================================================================
endmodule

testbench.vcd
$date
	Tue Oct 25 17:44:06 2022
$end
$version
	Icarus Verilog
$end
$timescale
	1ps
$end
$scope module backend_tb $end
$var wire 1 ! sdin $end
$var wire 1 " sclk $end
$var wire 1 # resetbvco $end
$var wire 1 $ resetbAll $end
$var wire 1 % resetb2 $end
$var wire 1 & resetb1 $end
$var wire 1 ' ready $end
$var wire 3 ( gainA2 [2:0] $end
$var wire 2 ) gainA1 [1:0] $end
$var reg 1 * main_clk $end
$var reg 1 + resetbFPGA $end
$var reg 1 , vco_clk $end
$scope module FPGA_obj $end
$var wire 1 * i_mainclk $end
$var wire 1 + i_resetbFPGA $end
$var wire 1 ' i_ready $end
$var parameter 32 - opcode_gainA1 $end
$var parameter 32 . opcode_gainA2 $end
$var parameter 32 / sIDLE $end
$var parameter 32 0 sPROGRAM $end
$var parameter 32 1 sRESET $end
$var reg 2 2 FPGAstate [1:0] $end
$var reg 4 3 count [3:0] $end
$var reg 1 4 mainclkby16 $end
$var reg 1 5 mainclkby2 $end
$var reg 1 6 mainclkby4 $end
$var reg 1 7 mainclkby8 $end
$var reg 1 $ o_resetbAll $end
$var reg 1 " o_sclk $end
$var reg 1 ! o_sdout $end
$upscope $end
$scope module backend_obj $end
$var wire 1 * i_clk $end
$var wire 1 $ i_resetbAll $end
$var wire 1 " i_sclk $end
$var wire 1 ! i_sdin $end
$var wire 1 , i_vco_clk $end
$var reg 1 8 k $end
$var reg 2 9 o_gainA1 [1:0] $end
$var reg 3 : o_gainA2 [2:0] $end
$var reg 1 ' o_ready $end
$var reg 1 & o_resetb1 $end
$var reg 1 % o_resetb2 $end
$var reg 1 # o_resetbvco $end
$var reg 11 ; vco_freq [10:0] $end
$var integer 32 < ans [31:0] $end
$var integer 32 = i [31:0] $end
$var integer 32 > mainf [31:0] $end
$var integer 32 ? vcof [31:0] $end
$upscope $end
$upscope $end
$enddefinitions $end
$comment Show the parameter values. $end
$dumpall
b0 1
b1 0
b10 /
b111 .
b11 -
$end
#0
$dumpvars
b0 ?
b0 >
bx =
b0 <
b0 ;
b0 :
b0 9
08
07
06
05
04
b0 3
b0 2
0,
0+
0*
b0 )
b0 (
0'
0&
0%
0$
0#
1"
0!
$end
#555
1,
#1000
1+
#1110
0,
#1665
1,
#2220
0,
#2500
b1 3
14
17
16
15
b1 2
1*
#2775
1,
#3330
0,
#3885
1,
#4440
0,
#4995
1,
#5000
0*
#5550
0,
#6105
1,
#6660
0,
#7215
1,
#7500
b1 ?
b1 >
18
b0 =
1$
05
1*
#7770
0,
#8325
b10 ?
1,
#8880
0,
#9435
b11 ?
1,
#9990
0,
#10000
0*
#10545
b100 ?
1,
#11100
0,
#11655
b101 ?
1,
#12210
0,
#12500
06
15
b10 >
1*
#12765
b110 ?
1,
#13320
0,
#13875
b111 ?
1,
#14430
0,
#14985
b1000 ?
1,
#15000
0*
#15540
0,
#16095
b1001 ?
1,
#16650
0,
#17205
b1010 ?
1,
#17500
05
b11 >
1*
#17760
0,
#18315
b1011 ?
1,
#18870
0,
#19425
b1100 ?
1,
#19980
0,
#20000
0*
#20535
b1101 ?
1,
#21090
0,
#21645
b1110 ?
1,
#22200
0,
#22500
07
16
15
b100 >
1*
#22755
b1111 ?
1,
#23310
0,
#23865
b10000 ?
1,
#24420
0,
#24975
b10001 ?
1,
#25000
0*
#25530
0,
#26085
b10010 ?
1,
#26640
0,
#27195
b10011 ?
1,
#27500
05
b101 >
1*
#27750
0,
#28305
b10100 ?
1,
#28860
0,
#29415
b10101 ?
1,
#29970
0,
#30000
0*
#30525
b10110 ?
1,
#31080
0,
#31635
b10111 ?
1,
#32190
0,
#32500
06
15
b110 >
1*
#32745
b11000 ?
1,
#33300
0,
#33855
b11001 ?
1,
#34410
0,
#34965
b11010 ?
1,
#35000
0*
#35520
0,
#36075
b11011 ?
1,
#36630
0,
#37185
b11100 ?
1,
#37500
05
b111 >
1*
#37740
0,
#38295
b11101 ?
1,
#38850
0,
#39405
b11110 ?
1,
#39960
0,
#40000
0*
#40515
b11111 ?
1,
#41070
0,
#41625
b100000 ?
1,
#42180
0,
#42500
04
17
16
15
b1000 >
1*
#42735
b100001 ?
1,
#43290
0,
#43845
b100010 ?
1,
#44400
0,
#44955
b100011 ?
1,
#45000
0*
#45510
0,
#46065
b100100 ?
1,
#46620
0,
#47175
b100101 ?
1,
#47500
05
b1001 >
1*
#47730
0,
#48285
b100110 ?
1,
#48840
0,
#49395
b100111 ?
1,
#49950
0,
#50000
0*
#50505
b101000 ?
1,
#51060
0,
#51615
b101001 ?
1,
#52170
0,
#52500
06
15
b1010 >
1*
#52725
b101010 ?
1,
#53280
0,
#53835
b101011 ?
1,
#54390
0,
#54945
b101100 ?
1,
#55000
0*
#55500
0,
#56055
b101101 ?
1,
#56610
0,
#57165
b101110 ?
1,
#57500
05
b1011 >
1*
#57720
0,
#58275
b101111 ?
1,
#58830
0,
#59385
b110000 ?
1,
#59940
0,
#60000
0*
#60495
b110001 ?
1,
#61050
0,
#61605
b110010 ?
1,
#62160
0,
#62500
07
16
15
b1100 >
1*
#62715
b110011 ?
1,
#63270
0,
#63825
b110100 ?
1,
#64380
0,
#64935
b110101 ?
1,
#65000
0*
#65490
0,
#66045
b110110 ?
1,
#66600
0,
#67155
b110111 ?
1,
#67500
05
b1101 >
1*
#67710
0,
#68265
b111000 ?
1,
#68820
0,
#69375
b111001 ?
1,
#69930
0,
#70000
0*
#70485
b111010 ?
1,
#71040
0,
#71595
b111011 ?
1,
#72150
0,
#72500
06
15
b1110 >
1*
#72705
b111100 ?
1,
#73260
0,
#73815
b111101 ?
1,
#74370
0,
#74925
b111110 ?
1,
#75000
0*
#75480
0,
#76035
b111111 ?
1,
#76590
0,
#77145
b1000000 ?
1,
#77500
05
b1111 >
1*
#77700
0,
#78255
b1000001 ?
1,
#78810
0,
#79365
b1000010 ?
1,
#79920
0,
#80000
0*
#80475
b1000011 ?
1,
#81030
0,
#81585
b1000100 ?
1,
#82140
0,
#82500
1!
b10 3
0"
14
17
16
15
b10000 >
1*
#82695
b1000101 ?
1,
#83250
0,
#83805
b1000110 ?
1,
#84360
0,
#84915
b1000111 ?
1,
#85000
0*
#85470
0,
#86025
b1001000 ?
1,
#86580
0,
#87135
b1001001 ?
1,
#87500
05
b10001 >
1*
#87690
0,
#88245
b1001010 ?
1,
#88800
0,
#89355
b1001011 ?
1,
#89910
0,
#90000
0*
#90465
b1001100 ?
1,
#91020
0,
#91575
b1001101 ?
1,
#92130
0,
#92500
06
15
b10010 >
1*
#92685
b1001110 ?
1,
#93240
0,
#93795
b1001111 ?
1,
#94350
0,
#94905
b1010000 ?
1,
#95000
0*
#95460
0,
#96015
b1010001 ?
1,
#96570
0,
#97125
b1010010 ?
1,
#97500
05
b10011 >
1*
#97680
0,
#98235
b1010011 ?
1,
#98790
0,
#99345
b1010100 ?
1,
#99900
0,
#100000
0*
#100455
b1010101 ?
1,
#101010
0,
#101565
b1010110 ?
1,
#102120
0,
#102500
07
16
15
b10100 >
1*
#102675
b1010111 ?
1,
#103230
0,
#103785
b1011000 ?
1,
#104340
0,
#104895
b1011001 ?
1,
#105000
0*
#105450
0,
#106005
b1011010 ?
1,
#106560
0,
#107115
b1011011 ?
1,
#107500
05
b10101 >
1*
#107670
0,
#108225
b1011100 ?
1,
#108780
0,
#109335
b1011101 ?
1,
#109890
0,
#110000
0*
#110445
b1011110 ?
1,
#111000
0,
#111555
b1011111 ?
1,
#112110
0,
#112500
06
15
b10110 >
1*
#112665
b1100000 ?
1,
#113220
0,
#113775
b1100001 ?
1,
#114330
0,
#114885
b1100010 ?
1,
#115000
0*
#115440
0,
#115995
b1100011 ?
1,
#116550
0,
#117105
b1100100 ?
1,
#117500
05
b10111 >
1*
#117660
0,
#118215
b1100101 ?
1,
#118770
0,
#119325
b1100110 ?
1,
#119880
0,
#120000
0*
#120435
b1100111 ?
1,
#120990
0,
#121545
b1101000 ?
1,
#122100
0,
#122500
04
17
16
15
b11000 >
1*
#122655
b1101001 ?
1,
#123210
0,
#123765
b1101010 ?
1,
#124320
0,
#124875
b1101011 ?
1,
#125000
0*
#125430
0,
#125985
b1101100 ?
1,
#126540
0,
#127095
b1101101 ?
1,
#127500
05
b11001 >
1*
#127650
0,
#128205
b1101110 ?
1,
#128760
0,
#129315
b1101111 ?
1,
#129870
0,
#130000
0*
#130425
b1110000 ?
1,
#130980
0,
#131535
b1110001 ?
1,
#132090
0,
#132500
06
15
b11010 >
1*
#132645
b1110010 ?
1,
#133200
0,
#133755
b1110011 ?
1,
#134310
0,
#134865
b1110100 ?
1,
#135000
0*
#135420
0,
#135975
b1110101 ?
1,
#136530
0,
#137085
b1110110 ?
1,
#137500
05
b11011 >
1*
#137640
0,
#138195
b1110111 ?
1,
#138750
0,
#139305
b1111000 ?
1,
#139860
0,
#140000
0*
#140415
b1111001 ?
1,
#140970
0,
#141525
b1111010 ?
1,
#142080
0,
#142500
07
16
15
b11100 >
1*
#142635
b1111011 ?
1,
#143190
0,
#143745
b1111100 ?
1,
#144300
0,
#144855
b1111101 ?
1,
#145000
0*
#145410
0,
#145965
b1111110 ?
1,
#146520
0,
#147075
b1111111 ?
1,
#147500
05
b11101 >
1*
#147630
0,
#148185
b10000000 ?
1,
#148740
0,
#149295
b10000001 ?
1,
#149850
0,
#150000
0*
#150405
b10000010 ?
1,
#150960
0,
#151515
b10000011 ?
1,
#152070
0,
#152500
06
15
b11110 >
1*
#152625
b10000100 ?
1,
#153180
0,
#153735
b10000101 ?
1,
#154290
0,
#154845
b10000110 ?
1,
#155000
0*
#155400
0,
#155955
b10000111 ?
1,
#156510
0,
#157065
b10001000 ?
1,
#157500
05
b11111 >
1*
#157620
0,
#158175
b10001001 ?
1,
#158730
0,
#159285
b10001010 ?
1,
#159840
0,
#160000
0*
#160395
b10001011 ?
1,
#160950
0,
#161505
b10001100 ?
1,
#162060
0,
#162500
b1 =
b1 )
b1 9
1"
b11 3
14
17
16
15
b100000 >
1*
#162615
b10001101 ?
1,
#163170
0,
#163725
b10001110 ?
1,
#164280
0,
#164835
b10001111 ?
1,
#165000
0*
#165390
0,
#165945
b10010000 ?
1,
#166500
0,
#167055
b10010001 ?
1,
#167500
05
b100001 >
1*
#167610
0,
#168165
b10010010 ?
1,
#168720
0,
#169275
b10010011 ?
1,
#169830
0,
#170000
0*
#170385
b10010100 ?
1,
#170940
0,
#171495
b10010101 ?
1,
#172050
0,
#172500
06
15
b100010 >
1*
#172605
b10010110 ?
1,
#173160
0,
#173715
b10010111 ?
1,
#174270
0,
#174825
b10011000 ?
1,
#175000
0*
#175380
0,
#175935
b10011001 ?
1,
#176490
0,
#177045
b10011010 ?
1,
#177500
05
b100011 >
1*
#177600
0,
#178155
b10011011 ?
1,
#178710
0,
#179265
b10011100 ?
1,
#179820
0,
#180000
0*
#180375
b10011101 ?
1,
#180930
0,
#181485
b10011110 ?
1,
#182040
0,
#182500
07
16
15
b100100 >
1*
#182595
b10011111 ?
1,
#183150
0,
#183705
b10100000 ?
1,
#184260
0,
#184815
b10100001 ?
1,
#185000
0*
#185370
0,
#185925
b10100010 ?
1,
#186480
0,
#187035
b10100011 ?
1,
#187500
05
b100101 >
1*
#187590
0,
#188145
b10100100 ?
1,
#188700
0,
#189255
b10100101 ?
1,
#189810
0,
#190000
0*
#190365
b10100110 ?
1,
#190920
0,
#191475
b10100111 ?
1,
#192030
0,
#192500
06
15
b100110 >
1*
#192585
b10101000 ?
1,
#193140
0,
#193695
b10101001 ?
1,
#194250
0,
#194805
b10101010 ?
1,
#195000
0*
#195360
0,
#195915
b10101011 ?
1,
#196470
0,
#197025
b10101100 ?
1,
#197500
05
b100111 >
1*
#197580
0,
#198135
b10101101 ?
1,
#198690
0,
#199245
b10101110 ?
1,
#199800
0,
#200000
0*
#200355
b10101111 ?
1,
#200910
0,
#201465
b10110000 ?
1,
#202020
0,
#202500
04
17
16
15
b101000 >
1*
#202575
b10110001 ?
1,
#203130
0,
#203685
b10110010 ?
1,
#204240
0,
#204795
b10110011 ?
1,
#205000
0*
#205350
0,
#205905
b10110100 ?
1,
#206460
0,
#207015
b10110101 ?
1,
#207500
05
b101001 >
1*
#207570
0,
#208125
b10110110 ?
1,
#208680
0,
#209235
b10110111 ?
1,
#209790
0,
#210000
0*
#210345
b10111000 ?
1,
#210900
0,
#211455
b10111001 ?
1,
#212010
0,
#212500
06
15
b101010 >
1*
#212565
b10111010 ?
1,
#213120
0,
#213675
b10111011 ?
1,
#214230
0,
#214785
b10111100 ?
1,
#215000
0*
#215340
0,
#215895
b10111101 ?
1,
#216450
0,
#217005
b10111110 ?
1,
#217500
05
b101011 >
1*
#217560
0,
#218115
b10111111 ?
1,
#218670
0,
#219225
b11000000 ?
1,
#219780
0,
#220000
0*
#220335
b11000001 ?
1,
#220890
0,
#221445
b11000010 ?
1,
#222000
0,
#222500
07
16
15
b101100 >
1*
#222555
b11000011 ?
1,
#223110
0,
#223665
b11000100 ?
1,
#224220
0,
#224775
b11000101 ?
1,
#225000
0*
#225330
0,
#225885
b11000110 ?
1,
#226440
0,
#226995
b11000111 ?
1,
#227500
05
b101101 >
1*
#227550
0,
#228105
b11001000 ?
1,
#228660
0,
#229215
b11001001 ?
1,
#229770
0,
#230000
0*
#230325
b11001010 ?
1,
#230880
0,
#231435
b11001011 ?
1,
#231990
0,
#232500
06
15
b101110 >
1*
#232545
b11001100 ?
1,
#233100
0,
#233655
b11001101 ?
1,
#234210
0,
#234765
b11001110 ?
1,
#235000
0*
#235320
0,
#235875
b11001111 ?
1,
#236430
0,
#236985
b11010000 ?
1,
#237500
05
b101111 >
1*
#237540
0,
#238095
b11010001 ?
1,
#238650
0,
#239205
b11010010 ?
1,
#239760
0,
#240000
0*
#240315
b11010011 ?
1,
#240870
0,
#241425
b11010100 ?
1,
#241980
0,
#242500
b100 3
0"
14
17
16
15
b110000 >
1*
#242535
b11010101 ?
1,
#243090
0,
#243645
b11010110 ?
1,
#244200
0,
#244755
b11010111 ?
1,
#245000
0*
#245310
0,
#245865
b11011000 ?
1,
#246420
0,
#246975
b11011001 ?
1,
#247500
05
b110001 >
1*
#247530
0,
#248085
b11011010 ?
1,
#248640
0,
#249195
b11011011 ?
1,
#249750
0,
#250000
0*
#250305
b11011100 ?
1,
#250860
0,
#251415
b11011101 ?
1,
#251970
0,
#252500
06
15
b110010 >
1*
#252525
b11011110 ?
1,
#253080
0,
#253635
b11011111 ?
1,
#254190
0,
#254745
b11100000 ?
1,
#255000
0*
#255300
0,
#255855
b11100001 ?
1,
#256410
0,
#256965
b11100010 ?
1,
#257500
05
b110011 >
1*
#257520
0,
#258075
b11100011 ?
1,
#258630
0,
#259185
b11100100 ?
1,
#259740
0,
#260000
0*
#260295
b11100101 ?
1,
#260850
0,
#261405
b11100110 ?
1,
#261960
0,
#262500
07
16
15
b110100 >
1*
#262515
b11100111 ?
1,
#263070
0,
#263625
b11101000 ?
1,
#264180
0,
#264735
b11101001 ?
1,
#265000
0*
#265290
0,
#265845
b11101010 ?
1,
#266400
0,
#266955
b11101011 ?
1,
#267500
05
b110101 >
1*
#267510
0,
#268065
b11101100 ?
1,
#268620
0,
#269175
b11101101 ?
1,
#269730
0,
#270000
0*
#270285
b11101110 ?
1,
#270840
0,
#271395
b11101111 ?
1,
#271950
0,
#272500
06
15
b110110 >
1*
#272505
b11110000 ?
1,
#273060
0,
#273615
b11110001 ?
1,
#274170
0,
#274725
b11110010 ?
1,
#275000
0*
#275280
0,
#275835
b11110011 ?
1,
#276390
0,
#276945
b11110100 ?
1,
#277500
05
b110111 >
0,
1*
#278055
b11110101 ?
1,
#278610
0,
#279165
b11110110 ?
1,
#279720
0,
#280000
0*
#280275
b11110111 ?
1,
#280830
0,
#281385
b11111000 ?
1,
#281940
0,
#282495
b11111001 ?
1,
#282500
04
17
16
15
b111000 >
1*
#283050
0,
#283605
b11111010 ?
1,
#284160
0,
#284715
b11111011 ?
1,
#285000
0*
#285270
0,
#285825
b11111100 ?
1,
#286380
0,
#286935
b11111101 ?
1,
#287490
0,
#287500
05
b111001 >
1*
#288045
b11111110 ?
1,
#288600
0,
#289155
b11111111 ?
1,
#289710
0,
#290000
0*
#290265
b100000000 ?
1,
#290820
0,
#291375
b100000001 ?
1,
#291930
0,
#292485
b100000010 ?
1,
#292500
06
15
b111010 >
1*
#293040
0,
#293595
b100000011 ?
1,
#294150
0,
#294705
b100000100 ?
1,
#295000
0*
#295260
0,
#295815
b100000101 ?
1,
#296370
0,
#296925
b100000110 ?
1,
#297480
0,
#297500
05
b111011 >
1*
#298035
b100000111 ?
1,
#298590
0,
#299145
b100001000 ?
1,
#299700
0,
#300000
0*
#300255
b100001001 ?
1,
#300810
0,
#301365
b100001010 ?
1,
#301920
0,
#302475
b100001011 ?
1,
#302500
07
16
15
b111100 >
1*
#303030
0,
#303585
b100001100 ?
1,
#304140
0,
#304695
b100001101 ?
1,
#305000
0*
#305250
0,
#305805
b100001110 ?
1,
#306360
0,
#306915
b100001111 ?
1,
#307470
0,
#307500
05
b111101 >
1*
#308025
b100010000 ?
1,
#308580
0,
#309135
b100010001 ?
1,
#309690
0,
#310000
0*
#310245
b100010010 ?
1,
#310800
0,
#311355
b100010011 ?
1,
#311910
0,
#312465
b100010100 ?
1,
#312500
06
15
b111110 >
1*
#313020
0,
#313575
b100010101 ?
1,
#314130
0,
#314685
b100010110 ?
1,
#315000
0*
#315240
0,
#315795
b100010111 ?
1,
#316350
0,
#316905
b100011000 ?
1,
#317460
0,
#317500
05
b111111 >
1*
#318015
b100011001 ?
1,
#318570
0,
#319125
b100011010 ?
1,
#319680
0,
#320000
0*
#320235
b100011011 ?
1,
#320790
0,
#321345
b100011100 ?
1,
#321900
0,
#322455
b100011101 ?
1,
#322500
b0 =
b11 )
b11 9
1"
b101 3
14
17
16
15
b1000000 >
1*
#323010
0,
#323565
b100011110 ?
1,
#324120
0,
#324675
b100011111 ?
1,
#325000
0*
#325230
0,
#325785
b100100000 ?
1,
#326340
0,
#326895
b100100001 ?
1,
#327450
0,
#327500
05
b1000001 >
1*
#328005
b100100010 ?
1,
#328560
0,
#329115
b100100011 ?
1,
#329670
0,
#330000
0*
#330225
b100100100 ?
1,
#330780
0,
#331335
b100100101 ?
1,
#331890
0,
#332445
b100100110 ?
1,
#332500
06
15
b1000010 >
1*
#333000
0,
#333555
b100100111 ?
1,
#334110
0,
#334665
b100101000 ?
1,
#335000
0*
#335220
0,
#335775
b100101001 ?
1,
#336330
0,
#336885
b100101010 ?
1,
#337440
0,
#337500
05
b1000011 >
1*
#337995
b100101011 ?
1,
#338550
0,
#339105
b100101100 ?
1,
#339660
0,
#340000
0*
#340215
b100101101 ?
1,
#340770
0,
#341325
b100101110 ?
1,
#341880
0,
#342435
b100101111 ?
1,
#342500
07
16
15
b1000100 >
1*
#342990
0,
#343545
b100110000 ?
1,
#344100
0,
#344655
b100110001 ?
1,
#345000
0*
#345210
0,
#345765
b100110010 ?
1,
#346320
0,
#346875
b100110011 ?
1,
#347430
0,
#347500
05
b1000101 >
1*
#347985
b100110100 ?
1,
#348540
0,
#349095
b100110101 ?
1,
#349650
0,
#350000
0*
#350205
b100110110 ?
1,
#350760
0,
#351315
b100110111 ?
1,
#351870
0,
#352425
b100111000 ?
1,
#352500
06
15
b1000110 >
1*
#352980
0,
#353535
b100111001 ?
1,
#354090
0,
#354645
b100111010 ?
1,
#355000
0*
#355200
0,
#355755
b100111011 ?
1,
#356310
0,
#356865
b100111100 ?
1,
#357420
0,
#357500
05
b1000111 >
1*
#357975
b100111101 ?
1,
#358530
0,
#359085
b100111110 ?
1,
#359640
0,
#360000
0*
#360195
b100111111 ?
1,
#360750
0,
#361305
b101000000 ?
1,
#361860
0,
#362415
b101000001 ?
1,
#362500
04
17
16
15
b1001000 >
1*
#362970
0,
#363525
b101000010 ?
1,
#364080
0,
#364635
b101000011 ?
1,
#365000
0*
#365190
0,
#365745
b101000100 ?
1,
#366300
0,
#366855
b101000101 ?
1,
#367410
0,
#367500
05
b1001001 >
1*
#367965
b101000110 ?
1,
#368520
0,
#369075
b101000111 ?
1,
#369630
0,
#370000
0*
#370185
b101001000 ?
1,
#370740
0,
#371295
b101001001 ?
1,
#371850
0,
#372405
b101001010 ?
1,
#372500
06
15
b1001010 >
1*
#372960
0,
#373515
b101001011 ?
1,
#374070
0,
#374625
b101001100 ?
1,
#375000
0*
#375180
0,
#375735
b101001101 ?
1,
#376290
0,
#376845
b101001110 ?
1,
#377400
0,
#377500
05
b1001011 >
1*
#377955
b101001111 ?
1,
#378510
0,
#379065
b101010000 ?
1,
